{
    "msg": "获取章节试题成功",
    "data": {
        "test": {
            "ReturnMessage": "取数据成功",
            "APPEName": "ZY_LCZY_YTMJ",
            "GenDate": "Tue May 14 2019 22:50:09 GMT+0800 (CST)",
            "StyleItems": [
                {
                    "StyleID": 1,
                    "Style": "A1型题",
                    "Explain": "A1型题：每一道考试题下面有A、B、C、D、E五个备选答案。请从中选择一个最佳答案。",
                    "Score": 1,
                    "Type": "ATEST",
                    "SubType": "",
                    "TestCount": 14,
                    "TestItems": [
                        {
                            "Title": "587ef17b83719cd1312ecabc3c1bd1067f5190ed9160760e1cf279954005ba7d",
                            "Explain": "氰化物毒性强烈、作用迅速。被食用后在肠道内水解释放出CN-，中毒原理是CN-与细胞色素（细胞色素aa[XB3.gif]）氧化酶中的Fe[SB3jia.gif]起反应，形成氰化细胞色素氧化酶，失去了递氧作用。故选D。",
                            "TestPoint": "",
                            "Answer": "D",
                            "Difficulty": "",
                            "SelectedItems": [
                                {
                                    "HasImg": 1,
                                    "ItemName": "A",
                                    "Content": "细胞色素c"
                                },
                                {
                                    "HasImg": 0,
                                    "ItemName": "B",
                                    "Content": "细胞色素b"
                                },
                                {
                                    "HasImg": 0,
                                    "ItemName": "C",
                                    "Content": "辅酶Q"
                                },
                                {
                                    "HasImg": 1,
                                    "ItemName": "D",
                                    "Content": "细胞色素aa[XB3.gif]"
                                },
                                {
                                    "HasImg": 1,
                                    "ItemName": "E",
                                    "Content": "细胞色素c[XB1.gif]"
                                }
                            ],
                            "StyleType": "ATEST",
                            "AllTestID": 41000043,
                            "ATestID": 41000043,
                            "SrcID": 9,
                            "SbjID": 37,
                            "CptID": 128,
                            "IsFav": 0,
                            "UserNoteContent": "",
                            "DealInfo": ""
                        },
                        {
                            "Title": "c579bbb4f89c699a47aafacb28d6d06cd2fab9ec1f04bc85a5f373d1f633b25fd8309b6b8ed11a7e2b844cf4f3bd8213c98926b2240ded8c2f84056601feca68ed5188bc3e9101e96abc1b948da790bdc6bc6d78e82f1c66",
                            "Explain": "反应产物都是CO[XB2.gif]、H[XB2.gif]O和能量。",
                            "TestPoint": "",
                            "Answer": "E",
                            "Difficulty": "",
                            "SelectedItems": [
                                {
                                    "HasImg": 1,
                                    "ItemName": "A",
                                    "Content": "都需催化剂"
                                },
                                {
                                    "HasImg": 0,
                                    "ItemName": "B",
                                    "Content": "都需在温和条件下进行"
                                },
                                {
                                    "HasImg": 0,
                                    "ItemName": "C",
                                    "Content": "都是逐步释放能量"
                                },
                                {
                                    "HasImg": 0,
                                    "ItemName": "D",
                                    "Content": "生成的终产物不同"
                                },
                                {
                                    "HasImg": 0,
                                    "ItemName": "E",
                                    "Content": "生成的终产物基本相同"
                                }
                            ],
                            "StyleType": "ATEST",
                            "AllTestID": 43000048,
                            "ATestID": 43000048,
                            "SrcID": 9,
                            "SbjID": 37,
                            "CptID": 128,
                            "IsFav": 0,
                            "UserNoteContent": "",
                            "DealInfo": ""
                        },
                        {
                            "Title": "002235026aa4a9226c94a6b1bb5c0dfca3571eaba021f9c64142476fcaf33f27ba9bdce13938798ad0156f5ec48fd2cc",
                            "Explain": "生物体内存在两条氧化呼吸链，即NADH氧化呼吸链和琥珀酸氧化呼吸链。NADPH不是呼吸链的组成成分。",
                            "TestPoint": "",
                            "Answer": "B",
                            "Difficulty": "",
                            "SelectedItems": [
                                {
                                    "HasImg": 1,
                                    "ItemName": "A",
                                    "Content": "C[XBzo.gif]Q"
                                },
                                {
                                    "HasImg": 0,
                                    "ItemName": "B",
                                    "Content": "NADPH"
                                },
                                {
                                    "HasImg": 0,
                                    "ItemName": "C",
                                    "Content": "FAD"
                                },
                                {
                                    "HasImg": 0,
                                    "ItemName": "D",
                                    "Content": "FMN"
                                },
                                {
                                    "HasImg": 0,
                                    "ItemName": "E",
                                    "Content": "以上均不是"
                                }
                            ],
                            "StyleType": "ATEST",
                            "AllTestID": 43000049,
                            "ATestID": 43000049,
                            "SrcID": 9,
                            "SbjID": 37,
                            "CptID": 128,
                            "IsFav": 0,
                            "UserNoteContent": "",
                            "DealInfo": ""
                        },
                        {
                            "Title": "17e764467b253f506d09b8e499cb049265606badfd5f372a63d59c4fdc8c5fe2d40b7860c1dff41b5b04b8acdf55735d",
                            "Explain": "FAD是递氢递电子体，能传递2H、2e。",
                            "TestPoint": "",
                            "Answer": "E",
                            "Difficulty": "",
                            "SelectedItems": [
                                {
                                    "HasImg": 1,
                                    "ItemName": "A",
                                    "Content": "是一种辅基"
                                },
                                {
                                    "HasImg": 0,
                                    "ItemName": "B",
                                    "Content": "递氢机制与FMN相同"
                                },
                                {
                                    "HasImg": 0,
                                    "ItemName": "C",
                                    "Content": "是递氢递电子体"
                                },
                                {
                                    "HasImg": 0,
                                    "ItemName": "D",
                                    "Content": "含1分子核黄素、1分子腺嘌呤，2分子核糖，2分子磷酸"
                                },
                                {
                                    "HasImg": 0,
                                    "ItemName": "E",
                                    "Content": "只传递电子，不传递质子"
                                }
                            ],
                            "StyleType": "ATEST",
                            "AllTestID": 43000050,
                            "ATestID": 43000050,
                            "SrcID": 9,
                            "SbjID": 37,
                            "CptID": 128,
                            "IsFav": 0,
                            "UserNoteContent": "",
                            "DealInfo": ""
                        },
                        {
                            "Title": "b5751abf3ce4938c4908732e184a77d676a71b223348eddc04654a0d9c31c6faae3ffb8a834db9f549c993564535980352c4e8d3f658463a",
                            "Explain": "不同物质脱下的氢进入呼吸链的部位不同，产生的ATP数也不相同，并不都是产生2.5个ATP。",
                            "TestPoint": "",
                            "Answer": "D",
                            "Difficulty": "",
                            "SelectedItems": [
                                {
                                    "HasImg": 1,
                                    "ItemName": "A",
                                    "Content": "NADH呼吸链是提供氧化磷酸化所需能量的主要途径"
                                },
                                {
                                    "HasImg": 0,
                                    "ItemName": "B",
                                    "Content": "呼吸链的各组分是按标准氧化还原电位，由低到高排列的"
                                },
                                {
                                    "HasImg": 0,
                                    "ItemName": "C",
                                    "Content": "电子传递方向从高还原电位流向高氧化电位"
                                },
                                {
                                    "HasImg": 0,
                                    "ItemName": "D",
                                    "Content": "每对氢原子氧化时都产生2.5个ATP"
                                },
                                {
                                    "HasImg": 0,
                                    "ItemName": "E",
                                    "Content": "不同物质脱下的氢进入呼吸链，产生的ATP数也不相同"
                                }
                            ],
                            "StyleType": "ATEST",
                            "AllTestID": 43000051,
                            "ATestID": 43000051,
                            "SrcID": 9,
                            "SbjID": 37,
                            "CptID": 128,
                            "IsFav": 0,
                            "UserNoteContent": "",
                            "DealInfo": ""
                        },
                        {
                            "Title": "f46adceaeb7fa54bf3cd1522f644dfef3525e8189a5a4ef7117692b506bd2b9d7e57c827a8236c5fa54b523c85efb03beb91fd2e02d35b9cc15de12d9cb41052",
                            "Explain": "呼吸链与磷酸化相偶联的3个部位分别是FMN(Fe-S)、Cytb→Cytcl→Cytc、Cytc→Cytaa[XB3.gif]。",
                            "TestPoint": "",
                            "Answer": "E",
                            "Difficulty": "",
                            "SelectedItems": [
                                {
                                    "HasImg": 1,
                                    "ItemName": "A",
                                    "Content": "FAD→FMN"
                                },
                                {
                                    "HasImg": 0,
                                    "ItemName": "B",
                                    "Content": "Cytc→Cyt"
                                },
                                {
                                    "HasImg": 0,
                                    "ItemName": "C",
                                    "Content": "CoQ→Cytb"
                                },
                                {
                                    "HasImg": 0,
                                    "ItemName": "D",
                                    "Content": "Cytc→Cyta"
                                },
                                {
                                    "HasImg": 0,
                                    "ItemName": "E",
                                    "Content": "FMN→CoQ"
                                }
                            ],
                            "StyleType": "ATEST",
                            "AllTestID": 43000052,
                            "ATestID": 43000052,
                            "SrcID": 9,
                            "SbjID": 37,
                            "CptID": 128,
                            "IsFav": 0,
                            "UserNoteContent": "",
                            "DealInfo": ""
                        },
                        {
                            "Title": "002235026aa4a9228bd0f5b7fbf55723b3cd921a6e757bc789e35cf82e95b0274754a62ff04d28f2aedb9f5edd8ae059de9897c04380702f",
                            "Explain": "脂酰CoA脱下的氢进入FADH[XB2.gif]氧化呼吸链，不进入NADH呼吸链。",
                            "TestPoint": "",
                            "Answer": "A",
                            "Difficulty": "",
                            "SelectedItems": [
                                {
                                    "HasImg": 1,
                                    "ItemName": "A",
                                    "Content": "脂酰CoA"
                                },
                                {
                                    "HasImg": 0,
                                    "ItemName": "B",
                                    "Content": "异柠檬酸"
                                },
                                {
                                    "HasImg": 0,
                                    "ItemName": "C",
                                    "Content": "丙酮酸"
                                },
                                {
                                    "HasImg": 0,
                                    "ItemName": "D",
                                    "Content": "β-羟丁酸"
                                },
                                {
                                    "HasImg": 0,
                                    "ItemName": "E",
                                    "Content": "α-羟丁酸"
                                }
                            ],
                            "StyleType": "ATEST",
                            "AllTestID": 43000053,
                            "ATestID": 43000053,
                            "SrcID": 9,
                            "SbjID": 37,
                            "CptID": 128,
                            "IsFav": 0,
                            "UserNoteContent": "",
                            "DealInfo": ""
                        },
                        {
                            "Title": "002235026aa4a9228bd0f5b7fbf55723b3cd921a6e757bc7cd0859e14f86141e212b0e33e6bb4ba8b4b7fda5fcdd4e0376393332d24043aa701feb71b92907657df81593529f6eec",
                            "Explain": "一对电子经琥珀酸氧化呼吸链传递，P/O比值约为1.5，如琥珀酸、α-磷酸甘油；一对电子经NADH氧化呼吸链传递，产生2.5个ATP，即P/O比值约为2.5，如β-羟丁酸、苹果酸、异柠檬酸、谷氨酸、丙酮酸等。",
                            "TestPoint": "",
                            "Answer": "E",
                            "Difficulty": "",
                            "SelectedItems": [
                                {
                                    "HasImg": 1,
                                    "ItemName": "A",
                                    "Content": "丙酮酸"
                                },
                                {
                                    "HasImg": 0,
                                    "ItemName": "B",
                                    "Content": "苹果酸"
                                },
                                {
                                    "HasImg": 0,
                                    "ItemName": "C",
                                    "Content": "谷氨酸"
                                },
                                {
                                    "HasImg": 0,
                                    "ItemName": "D",
                                    "Content": "β-羟丁酸"
                                },
                                {
                                    "HasImg": 0,
                                    "ItemName": "E",
                                    "Content": "琥珀酸"
                                }
                            ],
                            "StyleType": "ATEST",
                            "AllTestID": 43000054,
                            "ATestID": 43000054,
                            "SrcID": 9,
                            "SbjID": 37,
                            "CptID": 128,
                            "IsFav": 0,
                            "UserNoteContent": "",
                            "DealInfo": ""
                        },
                        {
                            "Title": "c579bbb4f89c699aacfdf01d3d958b8a24a14114ea706f0a4434a5593696a2947826e40f556475364163ece29c672e1d04fcec73609c3986533eb9cea556d191ef68bbd6db1ba469914694c81aa0f69dc25f90372dd4a1ef",
                            "Explain": "氧化磷酸化偶联机理的化学渗透学说，其基本要点是电子经呼吸链传递时，可将质子(H[SBjia.gif])从线粒体内膜基质侧泵到内膜胞浆侧，产生膜内外质子电化学梯度，以此储存能量。当质子顺浓度梯度回流时驱动ADP与Pi生成ATP。",
                            "TestPoint": "",
                            "Answer": "A",
                            "Difficulty": "",
                            "SelectedItems": [
                                {
                                    "HasImg": 1,
                                    "ItemName": "A",
                                    "Content": "呼吸链中各递氢体可将H[SBjia.gif]从线粒体膜内转运到膜外"
                                },
                                {
                                    "HasImg": 1,
                                    "ItemName": "B",
                                    "Content": "H[SBjia.gif]不能自由通过线粒体内膜"
                                },
                                {
                                    "HasImg": 0,
                                    "ItemName": "C",
                                    "Content": "在线粒体膜内外形成电化学梯度而储存能量"
                                },
                                {
                                    "HasImg": 1,
                                    "ItemName": "D",
                                    "Content": "线粒体膜内外形成的电化学梯度包括H[SBjia.gif]浓度梯度和跨膜电位差"
                                },
                                {
                                    "HasImg": 0,
                                    "ItemName": "E",
                                    "Content": "当质子顺浓度梯度回流时驱动ADP与Pi生成ATP"
                                }
                            ],
                            "StyleType": "ATEST",
                            "AllTestID": 43000055,
                            "ATestID": 43000055,
                            "SrcID": 9,
                            "SbjID": 37,
                            "CptID": 128,
                            "IsFav": 0,
                            "UserNoteContent": "",
                            "DealInfo": ""
                        },
                        {
                            "Title": "015b76d514fdac072a475014d05980d47b3bdd83d71a242582c913db9b0d4289bed72d9b124a1cefd03de7922296800c",
                            "Explain": "线粒体内参与氧化磷酸化的呼吸链主要有两条，即NADH氧化呼吸链和FADH[XB2.gif]氧化呼吸链，分别产生3分子和2分子ATP。",
                            "TestPoint": "",
                            "Answer": "C",
                            "Difficulty": "",
                            "SelectedItems": [
                                {
                                    "ItemName": "A",
                                    "Content": "氧化磷酸化过程涉及两种呼吸链"
                                },
                                {
                                    "ItemName": "B",
                                    "Content": "物质在氧化时伴有ADP磷酸化生成ATP的过程"
                                },
                                {
                                    "ItemName": "C",
                                    "Content": "电子分别经两种呼吸链传递至氧，均产生3分子ATP"
                                },
                                {
                                    "ItemName": "D",
                                    "Content": "氧化与磷酸化过程通过偶联产能"
                                },
                                {
                                    "ItemName": "E",
                                    "Content": "氧化磷酸化过程存在于线粒体内"
                                }
                            ],
                            "StyleType": "ATEST",
                            "AllTestID": 43014519,
                            "ATestID": 43014519,
                            "SrcID": 9,
                            "SbjID": 37,
                            "CptID": 128,
                            "IsFav": 0,
                            "UserNoteContent": "",
                            "DealInfo": ""
                        },
                        {
                            "Title": "015b76d514fdac072a475014d05980d4b49f49abb7f74d81e56ac28adeaa981db6dfd125ee121634",
                            "Explain": "在氧化磷酸化过程中，一对电子从FADH[XB2.gif]传递至氧产生1.5个ATP。由于FADH[XB2.gif]直接将电子传递给细胞色素C复合物，不经过NADH-CoQ还原酶，所以当一对电子从FADH[XB2.gif]传递至氧时只有6个质子由基质泵出，合成1分子ATP需4个质子，共形成1.5个ATP。E说法错误，其他选项说法皆正确，故本题选E。",
                            "TestPoint": "",
                            "Answer": "E",
                            "Difficulty": "",
                            "SelectedItems": [
                                {
                                    "ItemName": "A",
                                    "Content": "氧化磷酸化过程存在于线粒体内"
                                },
                                {
                                    "ItemName": "B",
                                    "Content": "物质在氧化时伴有ADP磷酸化生成ATP的过程"
                                },
                                {
                                    "ItemName": "C",
                                    "Content": "氧化磷酸化过程有两条呼吸链"
                                },
                                {
                                    "ItemName": "D",
                                    "Content": "P/O可以确定ATP的生成数"
                                },
                                {
                                    "ItemName": "E",
                                    "Content": "电子经呼吸链传递至氧产生3分子ATP"
                                }
                            ],
                            "StyleType": "ATEST",
                            "AllTestID": 43014520,
                            "ATestID": 43014520,
                            "SrcID": 9,
                            "SbjID": 37,
                            "CptID": 128,
                            "IsFav": 0,
                            "UserNoteContent": "",
                            "DealInfo": ""
                        },
                        {
                            "Title": "c5fb788f0285a9cc59f606e21e0af840ffb995dc0faedbf8a2bdbf05649ceaf5de2a3667fed1feff",
                            "Explain": "甲状腺素能诱导组织细胞膜Na[SBjia.gif]-KNa[SBjia.gif]-ATP酶的生成，使ATP水解生成ADP和Pi加快，使氧化磷酸化速度加快，耗氧量增加。",
                            "TestPoint": "",
                            "Answer": "C",
                            "Difficulty": "",
                            "SelectedItems": [
                                {
                                    "ItemName": "A",
                                    "Content": "生长激素"
                                },
                                {
                                    "ItemName": "B",
                                    "Content": "胰岛素"
                                },
                                {
                                    "ItemName": "C",
                                    "Content": "甲状腺素"
                                },
                                {
                                    "ItemName": "D",
                                    "Content": "胰高血糖素"
                                },
                                {
                                    "ItemName": "E",
                                    "Content": "甲状旁腺激素"
                                }
                            ],
                            "StyleType": "ATEST",
                            "AllTestID": 43014521,
                            "ATestID": 43014521,
                            "SrcID": 9,
                            "SbjID": 37,
                            "CptID": 128,
                            "IsFav": 0,
                            "UserNoteContent": "",
                            "DealInfo": ""
                        },
                        {
                            "Title": "b3ed3e486cc9796ef834ed161f87d7d2ea521c8a4cbee1f29dc35b0f4560adc35c6f075720d0725b9e5ac213eb0b8f878e1e57e08a4ab2c742ce6c88722ce413",
                            "Explain": "ADP或某些其他的核苷-5[SBDY.gif]-二磷酸的磷酸化是通过来自一个非核苷酸底物的磷酰基的转移实现的。这种磷酸化与电子的传递链无关。在分解代谢过程中，底物因脱氢、脱水等作用而使能量在分子内部重新分布，形成高能磷酸化合物，然后将高能磷酸基团转移到ADP形成ATP。",
                            "TestPoint": "",
                            "Answer": "B",
                            "Difficulty": "",
                            "SelectedItems": [
                                {
                                    "ItemName": "A",
                                    "Content": "CDP"
                                },
                                {
                                    "ItemName": "B",
                                    "Content": "ADP"
                                },
                                {
                                    "ItemName": "C",
                                    "Content": "GDP"
                                },
                                {
                                    "ItemName": "D",
                                    "Content": "TDP"
                                },
                                {
                                    "ItemName": "E",
                                    "Content": "UDP"
                                }
                            ],
                            "StyleType": "ATEST",
                            "AllTestID": 43014522,
                            "ATestID": 43014522,
                            "SrcID": 9,
                            "SbjID": 37,
                            "CptID": 128,
                            "IsFav": 0,
                            "UserNoteContent": "",
                            "DealInfo": ""
                        },
                        {
                            "Title": "f95a7712d0f9141d2cabe8cdad56c780f6616ec3233eb18b3452a852cb4fd82c715c75daf00e7b7e63a7c9ec61841001",
                            "Explain": "细胞色素C为生物氧化过程中的电子传递体，氧化呼吸链是由4种具有传递电子能力的复合体组成：①复合体工的作用是将NADH+H[SBjia.gif]中的电子传递给泛醌；②复合体Ⅱ的作用是将电子从琥珀酸传递到泛醌；③复合体Ⅲ的作用是将电子从还原型泛醌传递给细胞色素C；④复合体Ⅳ的作用是将电子从细胞色素C传递给氧。",
                            "TestPoint": "",
                            "Answer": "A",
                            "Difficulty": "",
                            "SelectedItems": [
                                {
                                    "ItemName": "A",
                                    "Content": "生物氧化"
                                },
                                {
                                    "ItemName": "B",
                                    "Content": "脂肪酸合成"
                                },
                                {
                                    "ItemName": "C",
                                    "Content": "糖酵解"
                                },
                                {
                                    "ItemName": "D",
                                    "Content": "肽键合成"
                                },
                                {
                                    "ItemName": "E",
                                    "Content": "叶酸还原"
                                }
                            ],
                            "StyleType": "ATEST",
                            "AllTestID": 43014523,
                            "ATestID": 43014523,
                            "SrcID": 9,
                            "SbjID": 37,
                            "CptID": 128,
                            "IsFav": 0,
                            "UserNoteContent": "",
                            "DealInfo": ""
                        }
                    ]
                },
                {
                    "StyleID": 3,
                    "Style": "B1型题",
                    "Explain": "B1型题：以下提供若干组考题，每组考题共用在考题前列出的A、B、C、D、E五个备选答案。请从中选择一个与问题关系最密切的答案。某个备选答案可能被选择一次、多次或不被选择。",
                    "Score": 1,
                    "Type": "BTEST",
                    "SubType": "单项",
                    "TestCount": 10,
                    "TestItems": [
                        {
                            "Title": "87db7841eb418c78f0e38f47b5c0778ca897d8d85f05d4a5c102b5d208bf0ba48feb205a484080c958e69abd38bea8ec",
                            "Explain": "生物转化反应可分为两相反应。第一相包括氧化、还原、水解反应，第二相即结合反应，葡萄糖醛酸结合反应属于第二相反应，故1题选D。胆汁酸合成过程中，羟化是最主要的变化。首先在7α-羟化酶催化下，胆固醇转变为7α-羟胆固醇，然后再转变成鹅脱氧胆酸或胆酸，后者的生成还需要在12位上进行羟化。7α-羟化是限速步骤，7α-羟化酶是限速酶，故2题选E。",
                            "TestPoint": "",
                            "Answer": "D",
                            "Difficulty": "",
                            "StyleType": "BTEST",
                            "SubStyleType": "ATEST",
                            "FrontTitle": "",
                            "SelectedItems": [
                                {
                                    "ItemName": "A",
                                    "Content": "氧化反应"
                                },
                                {
                                    "ItemName": "B",
                                    "Content": "还原反应"
                                },
                                {
                                    "ItemName": "C",
                                    "Content": "水解反应"
                                },
                                {
                                    "ItemName": "D",
                                    "Content": "葡萄糖醛酸结合反应"
                                },
                                {
                                    "ItemName": "E",
                                    "Content": "7α-羟化酶催化反应"
                                }
                            ],
                            "AllTestID": 41000044,
                            "BTestID": 41000024,
                            "SrcID": 9,
                            "SbjID": 37,
                            "CptID": 128,
                            "BTestItems": [
                                {
                                    "BTestItemID": 41000024,
                                    "Title": "87db7841eb418c78f0e38f47b5c0778ca897d8d85f05d4a5c102b5d208bf0ba48feb205a484080c958e69abd38bea8ec",
                                    "Explain": "生物转化反应可分为两相反应。第一相包括氧化、还原、水解反应，第二相即结合反应，葡萄糖醛酸结合反应属于第二相反应，故1题选D。胆汁酸合成过程中，羟化是最主要的变化。首先在7α-羟化酶催化下，胆固醇转变为7α-羟胆固醇，然后再转变成鹅脱氧胆酸或胆酸，后者的生成还需要在12位上进行羟化。7α-羟化是限速步骤，7α-羟化酶是限速酶，故2题选E。",
                                    "TestPoint": "",
                                    "Answer": "D",
                                    "DealInfo": ""
                                },
                                {
                                    "BTestItemID": 41000025,
                                    "Title": "e94ce60374c933aca268f6fb9478d67af1c6932886e39d5f143a985ef770398acda8ff666a5ee150ee3cc0e6efb1ad24d59649b8365fa9ae",
                                    "Explain": "生物转化反应可分为两相反应。第一相包括氧化、还原、水解反应，第二相即结合反应，葡萄糖醛酸结合反应属于第二相反应，故1题选D。胆汁酸合成过程中，羟化是最主要的变化。首先在7α-羟化酶催化下，胆固醇转变为7α-羟胆固醇，然后再转变成鹅脱氧胆酸或胆酸，后者的生成还需要在12位上进行羟化。7α-羟化是限速步骤，7α-羟化酶是限速酶，故2题选E。",
                                    "TestPoint": "",
                                    "Answer": "E",
                                    "DealInfo": ""
                                }
                            ],
                            "IsFav": 0,
                            "UserNoteContent": ""
                        },
                        {
                            "Title": "8f4c20fdcbbfe50849d3287b863995fe215551209e527c4bc501d5227cb50c1d1267495036eda600ccbb38dac957fee4",
                            "Explain": "组织的能量储存形式。",
                            "TestPoint": "",
                            "Answer": "A",
                            "Difficulty": "",
                            "StyleType": "BTEST",
                            "SubStyleType": "ATEST",
                            "FrontTitle": "",
                            "SelectedItems": [
                                {
                                    "ItemName": "A",
                                    "Content": "ATP"
                                },
                                {
                                    "ItemName": "B",
                                    "Content": "2，3-二磷酸甘油酸"
                                },
                                {
                                    "ItemName": "C",
                                    "Content": "磷酸肌酸"
                                },
                                {
                                    "ItemName": "D",
                                    "Content": "糖原"
                                },
                                {
                                    "ItemName": "E",
                                    "Content": "蛋白质"
                                }
                            ],
                            "AllTestID": 43000056,
                            "BTestID": 43000017,
                            "SrcID": 9,
                            "SbjID": 37,
                            "CptID": 128,
                            "BTestItems": [
                                {
                                    "BTestItemID": 43000017,
                                    "Title": "8f4c20fdcbbfe50849d3287b863995fe215551209e527c4bc501d5227cb50c1d1267495036eda600ccbb38dac957fee4",
                                    "Explain": "组织的能量储存形式。",
                                    "TestPoint": "",
                                    "Answer": "A",
                                    "DealInfo": ""
                                },
                                {
                                    "BTestItemID": 43000018,
                                    "Title": "813cc785ac8e47fea77512bbf0835392f0f0faa1bd656fcea9fff2ecb2fc3339bf8e6a227cf5b709",
                                    "Explain": "组织的能量储存形式。",
                                    "TestPoint": "",
                                    "Answer": "B",
                                    "DealInfo": ""
                                },
                                {
                                    "BTestItemID": 43000019,
                                    "Title": "ddfbd5059e312cec2083c5d049ae1b3e213b665935a8efb1c0eda3d98551cb6d2ef5adbcce067430a1841ccd98ceac71",
                                    "Explain": "",
                                    "TestPoint": "",
                                    "Answer": "C",
                                    "DealInfo": ""
                                },
                                {
                                    "BTestItemID": 43000020,
                                    "Title": "b4d16bb187158bdaac2cfc2e2fb65734fc08db3f1a7aa003b826c2cbfa948aa7",
                                    "Explain": "",
                                    "TestPoint": "",
                                    "Answer": "C",
                                    "DealInfo": "经核实，试题正确答案为C，已修改。",
                                    "OperateTime": "2018年12月12日",
                                    "OldTestJson": "{\"Title\":\"肌肉的能量储存形式是\",\"Explain\":\"\",\"TestPoint\":\"\",\"Answer\":\"D\",\"Difficulty\":\"\",\"StyleType\":\"BTEST\",\"SubStyleType\":\"ATEST\",\"FrontTitle\":\"\",\"SelectedItems\":[{\"ItemName\":\"A\",\"Content\":\"ATP\"},{\"ItemName\":\"B\",\"Content\":\"2，3-二磷酸甘油酸\"},{\"ItemName\":\"C\",\"Content\":\"磷酸肌酸\"},{\"ItemName\":\"D\",\"Content\":\"糖原\"},{\"ItemName\":\"E\",\"Content\":\"蛋白质\"}]}"
                                }
                            ],
                            "IsFav": 0,
                            "UserNoteContent": ""
                        },
                        {
                            "Title": "8f4c20fdcbbfe5086a3724c6bca5729b232b072fc189a6ae70b620969cf22d266a4f310db0dc2427db363e2a8d11e882",
                            "Explain": "",
                            "TestPoint": "",
                            "Answer": "D",
                            "Difficulty": "",
                            "StyleType": "BTEST",
                            "SubStyleType": "ATEST",
                            "FrontTitle": "",
                            "SelectedItems": [
                                {
                                    "ItemName": "A",
                                    "Content": "葡萄糖"
                                },
                                {
                                    "ItemName": "B",
                                    "Content": "硬脂酸"
                                },
                                {
                                    "ItemName": "C",
                                    "Content": "二磷酸腺苷"
                                },
                                {
                                    "ItemName": "D",
                                    "Content": "三磷酸腺苷"
                                },
                                {
                                    "ItemName": "E",
                                    "Content": "磷酸肌醇"
                                }
                            ],
                            "AllTestID": 43014524,
                            "BTestID": 43002676,
                            "SrcID": 9,
                            "SbjID": 37,
                            "CptID": 128,
                            "BTestItems": [
                                {
                                    "BTestItemID": 43002676,
                                    "Title": "8f4c20fdcbbfe5086a3724c6bca5729b232b072fc189a6ae70b620969cf22d266a4f310db0dc2427db363e2a8d11e882",
                                    "Explain": "",
                                    "TestPoint": "",
                                    "Answer": "D",
                                    "DealInfo": ""
                                },
                                {
                                    "BTestItemID": 43002677,
                                    "Title": "291e6937255517e631a0831d3b42154fc078002df640aac8a68382d01ded7813b724786176d0d9be",
                                    "Explain": "ATP是生命活动的直接供能物质，脂肪类物质的产能是最高的。",
                                    "TestPoint": "",
                                    "Answer": "B",
                                    "DealInfo": ""
                                }
                            ],
                            "IsFav": 0,
                            "UserNoteContent": ""
                        },
                        {
                            "Title": "d63aaa8fbf548af5e8c929db8864c0305fcd29e5e27eb7542642c0b8a09c7b90d3a97e5f065c076f",
                            "Explain": "ATP合酶是一个大的膜蛋白复合体，分子量在480～500kD，由两个主要组分构成，一个是疏水的F[XB0.gif]组分，另一个是亲水的F[XB1.gif]组分。",
                            "TestPoint": "",
                            "Answer": "B",
                            "Difficulty": "",
                            "StyleType": "BTEST",
                            "SubStyleType": "ATEST",
                            "FrontTitle": "",
                            "SelectedItems": [
                                {
                                    "ItemName": "A",
                                    "Content": "结合CDP后发生构象改变"
                                },
                                {
                                    "ItemName": "B",
                                    "Content": "具有ATP合酶活性"
                                },
                                {
                                    "ItemName": "C",
                                    "Content": "含有寡霉素敏感蛋白"
                                },
                                {
                                    "ItemName": "D",
                                    "Content": "存在单加氧酶"
                                },
                                {
                                    "ItemName": "E",
                                    "Content": "存在H[SBjia.gif]通道"
                                }
                            ],
                            "AllTestID": 43014525,
                            "BTestID": 43002678,
                            "SrcID": 9,
                            "SbjID": 37,
                            "CptID": 128,
                            "BTestItems": [
                                {
                                    "BTestItemID": 43002678,
                                    "Title": "d63aaa8fbf548af5e8c929db8864c0305fcd29e5e27eb7542642c0b8a09c7b90d3a97e5f065c076f",
                                    "Explain": "ATP合酶是一个大的膜蛋白复合体，分子量在480～500kD，由两个主要组分构成，一个是疏水的F[XB0.gif]组分，另一个是亲水的F[XB1.gif]组分。",
                                    "TestPoint": "",
                                    "Answer": "B",
                                    "DealInfo": "经核实，增加试题解析。",
                                    "OperateTime": "2018年12月18日",
                                    "OldTestJson": "{\"Title\":\"线粒体内膜复合物V的F[XB1.gif]\",\"Explain\":\"\",\"TestPoint\":\"\",\"Answer\":\"B\",\"Difficulty\":\"\",\"StyleType\":\"BTEST\",\"SubStyleType\":\"ATEST\",\"FrontTitle\":\"\",\"SelectedItems\":[{\"ItemName\":\"A\",\"Content\":\"结合CDP后发生构象改变\"},{\"ItemName\":\"B\",\"Content\":\"具有ATP合酶活性\"},{\"ItemName\":\"C\",\"Content\":\"含有寡霉素敏感蛋白\"},{\"ItemName\":\"D\",\"Content\":\"存在单加氧酶\"},{\"ItemName\":\"E\",\"Content\":\"存在H[SBjia.gif]通道\"}]}"
                                },
                                {
                                    "BTestItemID": 43002679,
                                    "Title": "d63aaa8fbf548af5e8c929db8864c0305fcd29e5e27eb7542642c0b8a09c7b90c2c9bbaf9a28e285",
                                    "Explain": "ATP合酶主要由F[XB1.gif]和F[XB0.gif]组成。F[XB1.gif]在线粒体内膜的基质侧形成颗粒状突起，其功能是催化生成ATP。F[XB0.gif]镶嵌在线粒体内膜中，起质子通道作用。",
                                    "TestPoint": "",
                                    "Answer": "E",
                                    "DealInfo": ""
                                }
                            ],
                            "IsFav": 0,
                            "UserNoteContent": ""
                        }
                    ]
                }
            ]
        },
        "isVip": 0,
        "testInfo": [
            {
                "AllTestID": 41000043,
                "ChildTableID": -1,
                "Correction": [],
                "Statistics": {
                    "Correction": [],
                    "Test": {
                        "AppID": 1328,
                        "AllTestID": 41000043,
                        "ChildTableID": -1,
                        "UserCount": 4068,
                        "RightCount": 1968,
                        "FavCount": 122,
                        "DiscussionCount": 0,
                        "ExplainCount": 0,
                        "ConcernCount": 78
                    }
                },
                "Analysis": [],
                "KnowledgePoint": {
                    "Summary": null,
                    "KnowledgeText": null,
                    "AllTestID": 41000043,
                    "ChildTableID": -1
                },
                "DiscussionCount": 0,
                "ExplainCount": 0,
                "ConcernCount": 78
            },
            {
                "AllTestID": 43000048,
                "ChildTableID": -1,
                "Correction": [],
                "Statistics": {
                    "Correction": [],
                    "Test": {
                        "AppID": 1328,
                        "AllTestID": 43000048,
                        "ChildTableID": -1,
                        "UserCount": 3702,
                        "RightCount": 2389,
                        "FavCount": 46,
                        "DiscussionCount": 0,
                        "ExplainCount": 0,
                        "ConcernCount": 24
                    }
                },
                "Analysis": [],
                "KnowledgePoint": {
                    "Summary": null,
                    "KnowledgeText": null,
                    "AllTestID": 43000048,
                    "ChildTableID": -1
                },
                "DiscussionCount": 0,
                "ExplainCount": 0,
                "ConcernCount": 24
            },
            {
                "AllTestID": 43000049,
                "ChildTableID": -1,
                "Correction": [],
                "Statistics": {
                    "Correction": [],
                    "Test": {
                        "AppID": 1328,
                        "AllTestID": 43000049,
                        "ChildTableID": -1,
                        "UserCount": 3665,
                        "RightCount": 1998,
                        "FavCount": 91,
                        "DiscussionCount": 2,
                        "ExplainCount": 0,
                        "ConcernCount": 41
                    }
                },
                "Analysis": [],
                "KnowledgePoint": {
                    "Summary": null,
                    "KnowledgeText": null,
                    "AllTestID": 43000049,
                    "ChildTableID": -1
                },
                "DiscussionCount": 2,
                "ExplainCount": 0,
                "ConcernCount": 41
            },
            {
                "AllTestID": 43000050,
                "ChildTableID": -1,
                "Correction": [],
                "Statistics": {
                    "Correction": [],
                    "Test": {
                        "AppID": 1328,
                        "AllTestID": 43000050,
                        "ChildTableID": -1,
                        "UserCount": 3486,
                        "RightCount": 2355,
                        "FavCount": 77,
                        "DiscussionCount": 2,
                        "ExplainCount": 0,
                        "ConcernCount": 60
                    }
                },
                "Analysis": [],
                "KnowledgePoint": {
                    "Summary": null,
                    "KnowledgeText": null,
                    "AllTestID": 43000050,
                    "ChildTableID": -1
                },
                "DiscussionCount": 2,
                "ExplainCount": 0,
                "ConcernCount": 60
            },
            {
                "AllTestID": 43000051,
                "ChildTableID": -1,
                "Correction": [],
                "Statistics": {
                    "Correction": [],
                    "Test": {
                        "AppID": 1328,
                        "AllTestID": 43000051,
                        "ChildTableID": -1,
                        "UserCount": 3240,
                        "RightCount": 2095,
                        "FavCount": 67,
                        "DiscussionCount": 0,
                        "ExplainCount": 0,
                        "ConcernCount": 42
                    }
                },
                "Analysis": [],
                "KnowledgePoint": {
                    "Summary": null,
                    "KnowledgeText": null,
                    "AllTestID": 43000051,
                    "ChildTableID": -1
                },
                "DiscussionCount": 0,
                "ExplainCount": 0,
                "ConcernCount": 42
            },
            {
                "AllTestID": 43000052,
                "ChildTableID": -1,
                "Correction": [],
                "Statistics": {
                    "Correction": [],
                    "Test": {
                        "AppID": 1328,
                        "AllTestID": 43000052,
                        "ChildTableID": -1,
                        "UserCount": 3150,
                        "RightCount": 1712,
                        "FavCount": 106,
                        "DiscussionCount": 0,
                        "ExplainCount": 0,
                        "ConcernCount": 57
                    }
                },
                "Analysis": [],
                "KnowledgePoint": {
                    "Summary": null,
                    "KnowledgeText": null,
                    "AllTestID": 43000052,
                    "ChildTableID": -1
                },
                "DiscussionCount": 0,
                "ExplainCount": 0,
                "ConcernCount": 57
            },
            {
                "AllTestID": 43000053,
                "ChildTableID": -1,
                "Correction": [],
                "Statistics": {
                    "Correction": [],
                    "Test": {
                        "AppID": 1328,
                        "AllTestID": 43000053,
                        "ChildTableID": -1,
                        "UserCount": 3155,
                        "RightCount": 1444,
                        "FavCount": 115,
                        "DiscussionCount": 0,
                        "ExplainCount": 0,
                        "ConcernCount": 53
                    }
                },
                "Analysis": [],
                "KnowledgePoint": {
                    "Summary": null,
                    "KnowledgeText": null,
                    "AllTestID": 43000053,
                    "ChildTableID": -1
                },
                "DiscussionCount": 0,
                "ExplainCount": 0,
                "ConcernCount": 53
            },
            {
                "AllTestID": 43000054,
                "ChildTableID": -1,
                "Correction": [],
                "Statistics": {
                    "Correction": [],
                    "Test": {
                        "AppID": 1328,
                        "AllTestID": 43000054,
                        "ChildTableID": -1,
                        "UserCount": 3061,
                        "RightCount": 1507,
                        "FavCount": 97,
                        "DiscussionCount": 0,
                        "ExplainCount": 0,
                        "ConcernCount": 58
                    }
                },
                "Analysis": [],
                "KnowledgePoint": {
                    "Summary": null,
                    "KnowledgeText": null,
                    "AllTestID": 43000054,
                    "ChildTableID": -1
                },
                "DiscussionCount": 0,
                "ExplainCount": 0,
                "ConcernCount": 58
            },
            {
                "AllTestID": 43000055,
                "ChildTableID": -1,
                "Correction": [],
                "Statistics": {
                    "Correction": [],
                    "Test": {
                        "AppID": 1328,
                        "AllTestID": 43000055,
                        "ChildTableID": -1,
                        "UserCount": 3045,
                        "RightCount": 1317,
                        "FavCount": 84,
                        "DiscussionCount": 0,
                        "ExplainCount": 0,
                        "ConcernCount": 41
                    }
                },
                "Analysis": [],
                "KnowledgePoint": {
                    "Summary": null,
                    "KnowledgeText": null,
                    "AllTestID": 43000055,
                    "ChildTableID": -1
                },
                "DiscussionCount": 0,
                "ExplainCount": 0,
                "ConcernCount": 41
            },
            {
                "AllTestID": 43014519,
                "ChildTableID": -1,
                "Correction": [],
                "Statistics": {
                    "Correction": [],
                    "Test": {
                        "AppID": 1328,
                        "AllTestID": 43014519,
                        "ChildTableID": -1,
                        "UserCount": 2462,
                        "RightCount": 2079,
                        "FavCount": 31,
                        "DiscussionCount": 0,
                        "ExplainCount": 0,
                        "ConcernCount": 20
                    }
                },
                "Analysis": [],
                "KnowledgePoint": {
                    "Summary": null,
                    "KnowledgeText": null,
                    "AllTestID": 43014519,
                    "ChildTableID": -1
                },
                "DiscussionCount": 0,
                "ExplainCount": 0,
                "ConcernCount": 20
            },
            {
                "AllTestID": 43014520,
                "ChildTableID": -1,
                "Correction": [],
                "Statistics": {
                    "Correction": [],
                    "Test": {
                        "AppID": 1328,
                        "AllTestID": 43014520,
                        "ChildTableID": -1,
                        "UserCount": 2658,
                        "RightCount": 2133,
                        "FavCount": 35,
                        "DiscussionCount": 0,
                        "ExplainCount": 0,
                        "ConcernCount": 15
                    }
                },
                "Analysis": [],
                "KnowledgePoint": {
                    "Summary": null,
                    "KnowledgeText": null,
                    "AllTestID": 43014520,
                    "ChildTableID": -1
                },
                "DiscussionCount": 0,
                "ExplainCount": 0,
                "ConcernCount": 15
            },
            {
                "AllTestID": 43014521,
                "ChildTableID": -1,
                "Correction": [],
                "Statistics": {
                    "Correction": [],
                    "Test": {
                        "AppID": 1328,
                        "AllTestID": 43014521,
                        "ChildTableID": -1,
                        "UserCount": 2755,
                        "RightCount": 1690,
                        "FavCount": 64,
                        "DiscussionCount": 0,
                        "ExplainCount": 0,
                        "ConcernCount": 19
                    }
                },
                "Analysis": [],
                "KnowledgePoint": {
                    "Summary": null,
                    "KnowledgeText": null,
                    "AllTestID": 43014521,
                    "ChildTableID": -1
                },
                "DiscussionCount": 0,
                "ExplainCount": 0,
                "ConcernCount": 19
            },
            {
                "AllTestID": 43014522,
                "ChildTableID": -1,
                "Correction": [],
                "Statistics": {
                    "Correction": [],
                    "Test": {
                        "AppID": 1328,
                        "AllTestID": 43014522,
                        "ChildTableID": -1,
                        "UserCount": 2570,
                        "RightCount": 1972,
                        "FavCount": 28,
                        "DiscussionCount": 0,
                        "ExplainCount": 0,
                        "ConcernCount": 21
                    }
                },
                "Analysis": [],
                "KnowledgePoint": {
                    "Summary": null,
                    "KnowledgeText": null,
                    "AllTestID": 43014522,
                    "ChildTableID": -1
                },
                "DiscussionCount": 0,
                "ExplainCount": 0,
                "ConcernCount": 21
            },
            {
                "AllTestID": 43014523,
                "ChildTableID": -1,
                "Correction": [],
                "Statistics": {
                    "Correction": [],
                    "Test": {
                        "AppID": 1328,
                        "AllTestID": 43014523,
                        "ChildTableID": -1,
                        "UserCount": 2428,
                        "RightCount": 1776,
                        "FavCount": 42,
                        "DiscussionCount": 0,
                        "ExplainCount": 0,
                        "ConcernCount": 18
                    }
                },
                "Analysis": [],
                "KnowledgePoint": {
                    "Summary": null,
                    "KnowledgeText": null,
                    "AllTestID": 43014523,
                    "ChildTableID": -1
                },
                "DiscussionCount": 0,
                "ExplainCount": 0,
                "ConcernCount": 18
            },
            {
                "AllTestID": 41000044,
                "ChildTableID": 41000024,
                "Correction": [],
                "Statistics": {
                    "Correction": [],
                    "Test": {
                        "AppID": 1328,
                        "AllTestID": 41000044,
                        "ChildTableID": 41000024,
                        "UserCount": 2664,
                        "RightCount": 1492,
                        "FavCount": 67,
                        "DiscussionCount": 0,
                        "ExplainCount": 0,
                        "ConcernCount": 36
                    }
                },
                "Analysis": [],
                "KnowledgePoint": {
                    "Summary": null,
                    "KnowledgeText": null,
                    "AllTestID": 41000044,
                    "ChildTableID": 41000024
                },
                "DiscussionCount": 0,
                "ExplainCount": 0,
                "ConcernCount": 36
            },
            {
                "AllTestID": 41000044,
                "ChildTableID": 41000025,
                "Correction": [],
                "Statistics": {
                    "Correction": [],
                    "Test": {
                        "AppID": 1328,
                        "AllTestID": 41000044,
                        "ChildTableID": 41000025,
                        "UserCount": 2559,
                        "RightCount": 1767,
                        "FavCount": 47,
                        "DiscussionCount": 0,
                        "ExplainCount": 0,
                        "ConcernCount": 26
                    }
                },
                "Analysis": [],
                "KnowledgePoint": {
                    "Summary": null,
                    "KnowledgeText": null,
                    "AllTestID": 41000044,
                    "ChildTableID": 41000025
                },
                "DiscussionCount": 0,
                "ExplainCount": 0,
                "ConcernCount": 26
            },
            {
                "AllTestID": 43000056,
                "ChildTableID": 43000017,
                "Correction": [],
                "Statistics": {
                    "Correction": [],
                    "Test": {
                        "AppID": 1328,
                        "AllTestID": 43000056,
                        "ChildTableID": 43000017,
                        "UserCount": 2465,
                        "RightCount": 2130,
                        "FavCount": 15,
                        "DiscussionCount": 0,
                        "ExplainCount": 0,
                        "ConcernCount": 6
                    }
                },
                "Analysis": [],
                "KnowledgePoint": {
                    "Summary": null,
                    "KnowledgeText": null,
                    "AllTestID": 43000056,
                    "ChildTableID": 43000017
                },
                "DiscussionCount": 0,
                "ExplainCount": 0,
                "ConcernCount": 6
            },
            {
                "AllTestID": 43000056,
                "ChildTableID": 43000018,
                "Correction": [],
                "Statistics": {
                    "Correction": [],
                    "Test": {
                        "AppID": 1328,
                        "AllTestID": 43000056,
                        "ChildTableID": 43000018,
                        "UserCount": 2810,
                        "RightCount": 1352,
                        "FavCount": 94,
                        "DiscussionCount": 0,
                        "ExplainCount": 0,
                        "ConcernCount": 18
                    }
                },
                "Analysis": [],
                "KnowledgePoint": {
                    "Summary": null,
                    "KnowledgeText": null,
                    "AllTestID": 43000056,
                    "ChildTableID": 43000018
                },
                "DiscussionCount": 0,
                "ExplainCount": 0,
                "ConcernCount": 18
            },
            {
                "AllTestID": 43000056,
                "ChildTableID": 43000019,
                "Correction": [],
                "Statistics": {
                    "Correction": [],
                    "Test": {
                        "AppID": 1328,
                        "AllTestID": 43000056,
                        "ChildTableID": 43000019,
                        "UserCount": 2773,
                        "RightCount": 1535,
                        "FavCount": 79,
                        "DiscussionCount": 0,
                        "ExplainCount": 0,
                        "ConcernCount": 11
                    }
                },
                "Analysis": [],
                "KnowledgePoint": {
                    "Summary": null,
                    "KnowledgeText": null,
                    "AllTestID": 43000056,
                    "ChildTableID": 43000019
                },
                "DiscussionCount": 0,
                "ExplainCount": 0,
                "ConcernCount": 11
            },
            {
                "AllTestID": 43000056,
                "ChildTableID": 43000020,
                "Correction": [],
                "Statistics": {
                    "Correction": [],
                    "Test": {
                        "AppID": 1328,
                        "AllTestID": 43000056,
                        "ChildTableID": 43000020,
                        "UserCount": 2774,
                        "RightCount": 1530,
                        "FavCount": 48,
                        "DiscussionCount": 2,
                        "ExplainCount": 0,
                        "ConcernCount": 9
                    }
                },
                "Analysis": [],
                "KnowledgePoint": {
                    "Summary": null,
                    "KnowledgeText": null,
                    "AllTestID": 43000056,
                    "ChildTableID": 43000020
                },
                "DiscussionCount": 2,
                "ExplainCount": 0,
                "ConcernCount": 9
            },
            {
                "AllTestID": 43014524,
                "ChildTableID": 43002676,
                "Correction": [],
                "Statistics": {
                    "Correction": [],
                    "Test": {
                        "AppID": 1328,
                        "AllTestID": 43014524,
                        "ChildTableID": 43002676,
                        "UserCount": 2339,
                        "RightCount": 1859,
                        "FavCount": 19,
                        "DiscussionCount": 0,
                        "ExplainCount": 0,
                        "ConcernCount": 8
                    }
                },
                "Analysis": [],
                "KnowledgePoint": {
                    "Summary": null,
                    "KnowledgeText": null,
                    "AllTestID": 43014524,
                    "ChildTableID": 43002676
                },
                "DiscussionCount": 0,
                "ExplainCount": 0,
                "ConcernCount": 8
            },
            {
                "AllTestID": 43014524,
                "ChildTableID": 43002677,
                "Correction": [],
                "Statistics": {
                    "Correction": [],
                    "Test": {
                        "AppID": 1328,
                        "AllTestID": 43014524,
                        "ChildTableID": 43002677,
                        "UserCount": 2633,
                        "RightCount": 1184,
                        "FavCount": 72,
                        "DiscussionCount": 0,
                        "ExplainCount": 0,
                        "ConcernCount": 12
                    }
                },
                "Analysis": [],
                "KnowledgePoint": {
                    "Summary": null,
                    "KnowledgeText": null,
                    "AllTestID": 43014524,
                    "ChildTableID": 43002677
                },
                "DiscussionCount": 0,
                "ExplainCount": 0,
                "ConcernCount": 12
            },
            {
                "AllTestID": 43014525,
                "ChildTableID": 43002678,
                "Correction": [],
                "Statistics": {
                    "Correction": [],
                    "Test": {
                        "AppID": 1328,
                        "AllTestID": 43014525,
                        "ChildTableID": 43002678,
                        "UserCount": 2954,
                        "RightCount": 1555,
                        "FavCount": 86,
                        "DiscussionCount": 3,
                        "ExplainCount": 0,
                        "ConcernCount": 41
                    }
                },
                "Analysis": [],
                "KnowledgePoint": {
                    "Summary": null,
                    "KnowledgeText": null,
                    "AllTestID": 43014525,
                    "ChildTableID": 43002678
                },
                "DiscussionCount": 3,
                "ExplainCount": 0,
                "ConcernCount": 41
            },
            {
                "AllTestID": 43014525,
                "ChildTableID": 43002679,
                "Correction": [],
                "Statistics": {
                    "Correction": [],
                    "Test": {
                        "AppID": 1328,
                        "AllTestID": 43014525,
                        "ChildTableID": 43002679,
                        "UserCount": 3016,
                        "RightCount": 1298,
                        "FavCount": 100,
                        "DiscussionCount": 0,
                        "ExplainCount": 0,
                        "ConcernCount": 44
                    }
                },
                "Analysis": [],
                "KnowledgePoint": {
                    "Summary": null,
                    "KnowledgeText": null,
                    "AllTestID": 43014525,
                    "ChildTableID": 43002679
                },
                "DiscussionCount": 0,
                "ExplainCount": 0,
                "ConcernCount": 44
            }
        ],
        "info": [],
        "encoded": 1,
        "examHistoryID": 0,
        "yimoinfo": [],
        "UserTime": 0
    },
    "status": 200
}