{
    "msg": "获取章节试题成功",
    "data": {
        "test": {
            "ReturnMessage": "取数据成功",
            "APPEName": "ZY_LCZY_YTMJ",
            "GenDate": "Wed May 15 2019 01:26:16 GMT+0800 (CST)",
            "StyleItems": [
                {
                    "StyleID": 1,
                    "Style": "A1型题",
                    "Explain": "A1型题：每一道考试题下面有A、B、C、D、E五个备选答案。请从中选择一个最佳答案。",
                    "Score": 1,
                    "Type": "ATEST",
                    "SubType": "",
                    "TestCount": 21,
                    "TestItems": [
                        {
                            "Title": "884b80f48772532569379a3f6047e555cb6008dcbde3a3d4dbae24e43c7067c7931fd72852b9cc0d2c100de4ea1a8a87cbfd836f69034b83cbdcf40cfb04d72945f55e4cce2e6277",
                            "Explain": "由于突发公共卫生事件具有突发性、公共性、危害性和复杂性等特点，所以应对突发公共卫生事件的有关人员在工作中应树立崇高的职业责任感和科学态度；勇于克服困难，具有献身精神；恪守职责和加强协作，发扬敬畏生命的人道主义精神。选项B是任何时候医务人员都不允许做的，故选B。",
                            "TestPoint": "",
                            "Answer": "B",
                            "Difficulty": "",
                            "SelectedItems": [
                                {
                                    "HasImg": 1,
                                    "ItemName": "A",
                                    "Content": "合理保护个人隐私"
                                },
                                {
                                    "HasImg": 0,
                                    "ItemName": "B",
                                    "Content": "个人利益优先，兼顾社会利益"
                                },
                                {
                                    "HasImg": 0,
                                    "ItemName": "C",
                                    "Content": "从业人员要增强职业责任感"
                                },
                                {
                                    "HasImg": 0,
                                    "ItemName": "D",
                                    "Content": "从业人员要有献身精神"
                                },
                                {
                                    "HasImg": 0,
                                    "ItemName": "E",
                                    "Content": "从业人员要与临床医生密切合作"
                                }
                            ],
                            "StyleType": "ATEST",
                            "AllTestID": 35000802,
                            "ATestID": 35000802,
                            "SrcID": 9,
                            "SbjID": 45,
                            "CptID": 161,
                            "IsFav": 0,
                            "UserNoteContent": "",
                            "DealInfo": ""
                        },
                        {
                            "Title": "1f1e2b8713f60e18e4b7335e1992a46009ee47eb856376e0",
                            "Explain": "公共卫生是研究预防疾病性质、任务、方法和规律的专门科学",
                            "TestPoint": "卫生服务体系与卫生管理",
                            "Answer": "B",
                            "Difficulty": "易",
                            "SelectedItems": [
                                {
                                    "HasImg": 1,
                                    "ItemName": "A",
                                    "Content": "疾病发生发展转归过程和专门规律的科学"
                                },
                                {
                                    "HasImg": 0,
                                    "ItemName": "B",
                                    "Content": "预防疾病性质、任务、方法和规律的专门科学"
                                },
                                {
                                    "HasImg": 0,
                                    "ItemName": "C",
                                    "Content": "疾病在人群的流行和采取有效措施"
                                },
                                {
                                    "HasImg": 0,
                                    "ItemName": "D",
                                    "Content": "疾病发生和消除疾病直接或间接因素"
                                },
                                {
                                    "HasImg": 0,
                                    "ItemName": "E",
                                    "Content": "对已发生的疾病的治疗和控制的科学"
                                }
                            ],
                            "StyleType": "ATEST",
                            "AllTestID": 43002874,
                            "ATestID": 43002874,
                            "SrcID": 9,
                            "SbjID": 45,
                            "CptID": 161,
                            "IsFav": 0,
                            "UserNoteContent": "",
                            "DealInfo": ""
                        },
                        {
                            "Title": "fcaaee417918661962ab6dcc80cbc85af161509bc42d1c45613c96898f1db89abc89c52e616aea574a973f6eb3abe4d59e7b97b218ec0374",
                            "Explain": "公共卫生工作的主要特点价值导向的超前性，服务对象的整体性，研究方法的独特性、工作效率的紧迫性、时效性，工作过程的长期性和艰巨性、工作效果评价的滞后性、效益影像的深远性",
                            "TestPoint": "卫生服务体系与卫生管理",
                            "Answer": "D",
                            "Difficulty": "易",
                            "SelectedItems": [
                                {
                                    "HasImg": 1,
                                    "ItemName": "A",
                                    "Content": "价值导向的超前性，服务对象的整体性，研究方法的独特性"
                                },
                                {
                                    "HasImg": 0,
                                    "ItemName": "B",
                                    "Content": "工作效率的紧迫性、时效性，工作过程的长期性和艰巨性"
                                },
                                {
                                    "HasImg": 0,
                                    "ItemName": "C",
                                    "Content": "工作效果评价的滞后性、效益影像的深远性"
                                },
                                {
                                    "HasImg": 0,
                                    "ItemName": "D",
                                    "Content": "社会效益、经济效益的可观性"
                                },
                                {
                                    "HasImg": 0,
                                    "ItemName": "E",
                                    "Content": "以上均不是"
                                }
                            ],
                            "StyleType": "ATEST",
                            "AllTestID": 43002875,
                            "ATestID": 43002875,
                            "SrcID": 9,
                            "SbjID": 45,
                            "CptID": 161,
                            "IsFav": 0,
                            "UserNoteContent": "",
                            "DealInfo": ""
                        },
                        {
                            "Title": "1f1e2b8713f60e18dcce9eef5cf1d1b41322cb8e8f041f0163060932274bf74db659f1493b966f10cd52f590bb57c81d272357105fec4ae8",
                            "Explain": "公共卫生工作中存在的主要问题、医学教育体制原因，使防和治产生\"裂痕\"、医学工作的分工，有部分预防工作者，没有向其他专业方向延伸、受科学发展所限制，使公共卫生、预防医学伦理原则、环境污染、食品研究、健康教育等伦理研究滞后、环境污染、食品安全和健康教育中的伦理问题越来越突出",
                            "TestPoint": "卫生服务体系与卫生管理",
                            "Answer": "D",
                            "Difficulty": "易",
                            "SelectedItems": [
                                {
                                    "HasImg": 1,
                                    "ItemName": "A",
                                    "Content": "医学教育体制原因，使防和治产生\"裂痕\""
                                },
                                {
                                    "HasImg": 0,
                                    "ItemName": "B",
                                    "Content": "医学工作的分工，有部分预防工作者，没有向其他专业方向延伸"
                                },
                                {
                                    "HasImg": 0,
                                    "ItemName": "C",
                                    "Content": "受科学发展所限制，使公共卫生、预防医学伦理原则、环境污染、食品研究、健康教育等伦理研究滞后"
                                },
                                {
                                    "HasImg": 0,
                                    "ItemName": "D",
                                    "Content": "我国人口众多，东西部经济发展不平衡，预防工作人员及经费不足，影响预防工作有效开展"
                                },
                                {
                                    "HasImg": 0,
                                    "ItemName": "E",
                                    "Content": "环境污染、食品安全和健康教育中的伦理问题越来越突出"
                                }
                            ],
                            "StyleType": "ATEST",
                            "AllTestID": 43002876,
                            "ATestID": 43002876,
                            "SrcID": 9,
                            "SbjID": 45,
                            "CptID": 161,
                            "IsFav": 0,
                            "UserNoteContent": "",
                            "DealInfo": ""
                        },
                        {
                            "Title": "262fb33b0383e288261844fcdb4369a13d4a2f08f7db1b1c89dfdf8130c13a96b8e49e78d39cbd384674c6681652ff9d",
                            "Explain": "大卫生观是一种现代卫生观,它以全民整体健康为内涵,强调卫生与社会经济协调发展,强调政府对人民健康负有责任,强调全社会、每个人积极参与卫生活动.按照大卫生观的要求,我们现在已经、今后还将继续在卫生目标、卫生服务以及卫生管理等方面进行适应性改革.",
                            "TestPoint": "医学工作科研的道德和医学道德",
                            "Answer": "A",
                            "Difficulty": "易",
                            "SelectedItems": [
                                {
                                    "HasImg": 1,
                                    "ItemName": "A",
                                    "Content": "着眼于大卫生系统的动态性与开放性和科学协调管理"
                                },
                                {
                                    "HasImg": 0,
                                    "ItemName": "B",
                                    "Content": "强调政府主导和全权管理"
                                },
                                {
                                    "HasImg": 0,
                                    "ItemName": "C",
                                    "Content": "以\"健康为人人，人人为健康\"和实现高级卫生保健、重点在城市为主要内容"
                                },
                                {
                                    "HasImg": 0,
                                    "ItemName": "D",
                                    "Content": "实现初级卫生保健，先城镇，后农村，逐步实现"
                                },
                                {
                                    "HasImg": 0,
                                    "ItemName": "E",
                                    "Content": "实现人人享有绝对健康的目标"
                                }
                            ],
                            "StyleType": "ATEST",
                            "AllTestID": 43002878,
                            "ATestID": 43002878,
                            "SrcID": 9,
                            "SbjID": 45,
                            "CptID": 161,
                            "IsFav": 0,
                            "UserNoteContent": "",
                            "DealInfo": ""
                        },
                        {
                            "Title": "d344be54e94ecb508b1952fd2a038c96d6cc7a221e40b419e9bba773f69d49be157b9ccc2fc7a780",
                            "Explain": "大卫生观是一种现代卫生观,它以全民整体健康为内涵,强调卫生与社会经济协调发展,强调政府对人民健康负有责任,强调全社会、每个人积极参与卫生活动.按照大卫生观的要求,我们现在已经、今后还将继续在卫生目标、卫生服务以及卫生管理等方面进行适应性改革.",
                            "TestPoint": "医学工作科研的道德和医学道德",
                            "Answer": "B",
                            "Difficulty": "易",
                            "SelectedItems": [
                                {
                                    "HasImg": 1,
                                    "ItemName": "A",
                                    "Content": "卫生事业结构简单，是一种刚起步的社会性事业"
                                },
                                {
                                    "HasImg": 0,
                                    "ItemName": "B",
                                    "Content": "生物、心理、社会医学模式的确立给人类健康事业带来全方位的影响"
                                },
                                {
                                    "HasImg": 0,
                                    "ItemName": "C",
                                    "Content": "重点是社会环境的完美化"
                                },
                                {
                                    "HasImg": 0,
                                    "ItemName": "D",
                                    "Content": "基础医学、临床医学、预防医学三大学科的基本内容"
                                },
                                {
                                    "HasImg": 0,
                                    "ItemName": "E",
                                    "Content": "保障人类健康仅取决于医学发展"
                                }
                            ],
                            "StyleType": "ATEST",
                            "AllTestID": 43002879,
                            "ATestID": 43002879,
                            "SrcID": 9,
                            "SbjID": 45,
                            "CptID": 161,
                            "IsFav": 0,
                            "UserNoteContent": "",
                            "DealInfo": ""
                        },
                        {
                            "Title": "98acce29f7652ad2633d2dd2903194a9c6c3ce33e72b6ccacf9a105eb8e77297f7ab569d5803f6aa187f09a3f49bfcb7",
                            "Explain": "改革城市卫生服务体系,积极发展社区卫生服务,逐步形成功能合理、方便群众的卫生服务网络\"",
                            "TestPoint": "卫生服务体系与卫生管理",
                            "Answer": "D",
                            "Difficulty": "易",
                            "SelectedItems": [
                                {
                                    "HasImg": 1,
                                    "ItemName": "A",
                                    "Content": "努力实现发展社区卫生服务，应对老龄化、城市化的战略举措"
                                },
                                {
                                    "HasImg": 0,
                                    "ItemName": "B",
                                    "Content": "承担医疗任务，负责预防保健工作"
                                },
                                {
                                    "HasImg": 0,
                                    "ItemName": "C",
                                    "Content": "改善社区的医疗卫生条件，为老、弱、病、残、少儿妇女的保健尽职尽责"
                                },
                                {
                                    "HasImg": 0,
                                    "ItemName": "D",
                                    "Content": "改革城市卫生服务体系，积极发展高端医疗卫生服务决策"
                                },
                                {
                                    "HasImg": 0,
                                    "ItemName": "E",
                                    "Content": "加强城市社区卫生人才队伍建设"
                                }
                            ],
                            "StyleType": "ATEST",
                            "AllTestID": 43002880,
                            "ATestID": 43002880,
                            "SrcID": 9,
                            "SbjID": 45,
                            "CptID": 161,
                            "IsFav": 0,
                            "UserNoteContent": "",
                            "DealInfo": ""
                        },
                        {
                            "Title": "a2b391354555a0910574c97b1a69d3893e7972d88b7f0166e5ce8e1609481ebcbcf38ea0187a74532b0da3a919f7df99",
                            "Explain": "预防医学控制疾病发生两大关口防疫和食品卫生",
                            "TestPoint": "卫生服务体系与卫生管理",
                            "Answer": "A",
                            "Difficulty": "易",
                            "SelectedItems": [
                                {
                                    "HasImg": 1,
                                    "ItemName": "A",
                                    "Content": "防疫和食品卫生"
                                },
                                {
                                    "HasImg": 0,
                                    "ItemName": "B",
                                    "Content": "管理与监督"
                                },
                                {
                                    "HasImg": 0,
                                    "ItemName": "C",
                                    "Content": "卫生知识的宣传与检查"
                                },
                                {
                                    "HasImg": 0,
                                    "ItemName": "D",
                                    "Content": "对传染病、地方病、流行病进行调查与隔离"
                                },
                                {
                                    "HasImg": 0,
                                    "ItemName": "E",
                                    "Content": "及时上报与及时隔离传染病"
                                }
                            ],
                            "StyleType": "ATEST",
                            "AllTestID": 43002881,
                            "ATestID": 43002881,
                            "SrcID": 9,
                            "SbjID": 45,
                            "CptID": 161,
                            "IsFav": 0,
                            "UserNoteContent": "",
                            "DealInfo": ""
                        },
                        {
                            "Title": "fcaaee4179186619015e1157c100f88b63cdc1307b770fa1ba3cc60bfc786fefcb4177f255193db19df4484bc78ecbb4a0807938fdab91e87892b908444da0cf",
                            "Explain": "公民都有权取得健康资源",
                            "TestPoint": "卫生服务体系与卫生管理",
                            "Answer": "E",
                            "Difficulty": "易",
                            "SelectedItems": [
                                {
                                    "HasImg": 1,
                                    "ItemName": "A",
                                    "Content": "尊重社会个人权利的方式，促进社会人群健康"
                                },
                                {
                                    "HasImg": 0,
                                    "ItemName": "B",
                                    "Content": "对公共卫生政策、方案、优先性提出评价，并把社会各种取向整合起来"
                                },
                                {
                                    "HasImg": 0,
                                    "ItemName": "C",
                                    "Content": "制定方案和政策，有效促进自然和社会环境的改善和实施"
                                },
                                {
                                    "HasImg": 0,
                                    "ItemName": "D",
                                    "Content": "公共卫生机构应当保护那些给个人和社会带来伤害的信息"
                                },
                                {
                                    "HasImg": 0,
                                    "ItemName": "E",
                                    "Content": "所有纳税的公民才有权取得健康资源"
                                }
                            ],
                            "StyleType": "ATEST",
                            "AllTestID": 43002882,
                            "ATestID": 43002882,
                            "SrcID": 9,
                            "SbjID": 45,
                            "CptID": 161,
                            "IsFav": 0,
                            "UserNoteContent": "",
                            "DealInfo": ""
                        },
                        {
                            "Title": "e10cc5fc6207a1e5f46917357125b128836818217dc834bf7d4f6427c389902266062cfb2a6ed11d1d65d2e44b987d9b120d9e18e1e6cf8e705ad4195f04176f46c192cc58ce6e87",
                            "Explain": "四大方面包括：①促进健康；②预防保健；③合理治疗；④社区康复八项要素①当前主要卫生问题及其预防和控制方法的健康教育；②增进必要的营养和供应充足的安全饮用水；③基本的环境卫生；④妇幼保健和计划生育；⑤主要传染病的预防接种；⑥地方病的预防与控制；⑦常见病和创伤的恰当处理；⑧基本药物的供应。",
                            "TestPoint": "卫生服务体系与卫生管理",
                            "Answer": "D",
                            "Difficulty": "易",
                            "SelectedItems": [
                                {
                                    "HasImg": 1,
                                    "ItemName": "A",
                                    "Content": "对重要保健问题进行宣传教育；开展包括计划生育在内的妇幼工作"
                                },
                                {
                                    "HasImg": 0,
                                    "ItemName": "B",
                                    "Content": "促进食品合理营养，保障安全用水供应；保障基本药物"
                                },
                                {
                                    "HasImg": 0,
                                    "ItemName": "C",
                                    "Content": "对传染病开展预防接种，预防和治疗地方病、常见病和外伤"
                                },
                                {
                                    "HasImg": 0,
                                    "ItemName": "D",
                                    "Content": "初级卫生保健的伦理审查工作"
                                },
                                {
                                    "HasImg": 0,
                                    "ItemName": "E",
                                    "Content": "采取基本公共卫生措施，保护精神健康"
                                }
                            ],
                            "StyleType": "ATEST",
                            "AllTestID": 43002883,
                            "ATestID": 43002883,
                            "SrcID": 9,
                            "SbjID": 45,
                            "CptID": 161,
                            "IsFav": 0,
                            "UserNoteContent": "",
                            "DealInfo": ""
                        },
                        {
                            "Title": "05cf43a1da3580986f2ee4df1a010356beca8d2f922bdb77842434e60f17b59a14442b236b43f9a27bbec109a276b0024fcd6b236c511215505b8ae9283c3490322a60ad0155b128",
                            "Explain": "卫生部门实施初级卫生保健的各项政策和具体措施",
                            "TestPoint": "卫生服务体系与卫生管理",
                            "Answer": "D",
                            "Difficulty": "易",
                            "SelectedItems": [
                                {
                                    "HasImg": 1,
                                    "ItemName": "A",
                                    "Content": "加强健康教育"
                                },
                                {
                                    "HasImg": 0,
                                    "ItemName": "B",
                                    "Content": "创建公众健康良好的生存环境"
                                },
                                {
                                    "HasImg": 0,
                                    "ItemName": "C",
                                    "Content": "公正、合理地分配卫生资源"
                                },
                                {
                                    "HasImg": 0,
                                    "ItemName": "D",
                                    "Content": "实施初级卫生保健的各项政策和具体措施"
                                },
                                {
                                    "HasImg": 0,
                                    "ItemName": "E",
                                    "Content": "促进人人维护健康"
                                }
                            ],
                            "StyleType": "ATEST",
                            "AllTestID": 43002884,
                            "ATestID": 43002884,
                            "SrcID": 9,
                            "SbjID": 45,
                            "CptID": 161,
                            "IsFav": 0,
                            "UserNoteContent": "",
                            "DealInfo": ""
                        },
                        {
                            "Title": "1bb02005de0427c173108147fa407254b00e60c274e368442849701c2ff3bcbd9bdad763963b1cc1",
                            "Explain": "基层工作者的行为规范是把维护基层人群的健康权益放在首位的道德观。",
                            "TestPoint": "",
                            "Answer": "E",
                            "Difficulty": "",
                            "SelectedItems": [
                                {
                                    "HasImg": 1,
                                    "ItemName": "A",
                                    "Content": "尊重病人人格，开展人性化服务和连续性服务"
                                },
                                {
                                    "HasImg": 0,
                                    "ItemName": "B",
                                    "Content": "言传身教，以身作则，做好宣传工作，落实各项公共卫生措施；做到分工协作，认真履行自己职责"
                                },
                                {
                                    "HasImg": 0,
                                    "ItemName": "C",
                                    "Content": "勤俭节约卫生资源"
                                },
                                {
                                    "HasImg": 0,
                                    "ItemName": "D",
                                    "Content": "树立新的卫生管理道德理念，完善为基层群众服务的三级医疗预防体系"
                                },
                                {
                                    "HasImg": 0,
                                    "ItemName": "E",
                                    "Content": "把维护所有人群的健康权益放在首位道德观"
                                }
                            ],
                            "StyleType": "ATEST",
                            "AllTestID": 43002885,
                            "ATestID": 43002885,
                            "SrcID": 9,
                            "SbjID": 45,
                            "CptID": 161,
                            "IsFav": 0,
                            "UserNoteContent": "",
                            "DealInfo": ""
                        },
                        {
                            "Title": "a9af24dfe89f78dc2f4e15e28893e6080a8268ac996a0e0a8da2ef291cf5330abe086b1575f3023b7a0c0d6cf96ec4d0",
                            "Explain": "目标任务开展多种形式的健康教育与健康促进活动，提高广大城乡居民健康教育普及率、疾病预防知识知晓率和健康行为形成率，降低传染病、慢性病以及慢性传染病和地方病等严重危害城乡居民健康的疾病的发病率，全面提高我县城乡居民健康水平和自我保护意识。",
                            "TestPoint": "健康教育",
                            "Answer": "C",
                            "Difficulty": "易",
                            "SelectedItems": [
                                {
                                    "HasImg": 1,
                                    "ItemName": "A",
                                    "Content": "建立或促进个人和社会对预防疾病和促进健康的大局观和全局责任感"
                                },
                                {
                                    "HasImg": 0,
                                    "ItemName": "B",
                                    "Content": "促进个体和社会做出决策，选择自己最喜欢的健康行为"
                                },
                                {
                                    "HasImg": 0,
                                    "ItemName": "C",
                                    "Content": "有效地促进全社会都来关心健康以及疾病预防问题"
                                },
                                {
                                    "HasImg": 0,
                                    "ItemName": "D",
                                    "Content": "对卫生专业人员及有关人员进行健康教育原则及实践方面的培训"
                                },
                                {
                                    "HasImg": 0,
                                    "ItemName": "E",
                                    "Content": "对老年人进行急救培训，减少突发疾病死亡率"
                                }
                            ],
                            "StyleType": "ATEST",
                            "AllTestID": 43002886,
                            "ATestID": 43002886,
                            "SrcID": 9,
                            "SbjID": 45,
                            "CptID": 161,
                            "IsFav": 0,
                            "UserNoteContent": "",
                            "DealInfo": ""
                        },
                        {
                            "Title": "f256d34925293e067e798b6ea718e2c3966bb4ffa44b19c70abbeefb7120fb85",
                            "Explain": "一、健康教育的意义健康教育是初级卫生保健八大要素之首《阿拉未图宣言》指出，健康教育是所有卫生保健问题、预防方法及控制措施中最为重要的，是否能实现初级卫生保健任务的关键。说明健康教育对实现所有健康目标、社会目标和经济目标中的地位和价值。第36届世界卫生大会和世界卫生组织委员会第68次会议，根据初级卫生保健原则来重新确定健康教育的作用，提出了“初级卫生保健中的健康教育新策略”，强调了健康教育是策略而不是工具。为了充分发挥健康教育的作用，应该把健康教育作为联系各部门的桥梁，以协调各部门共同参与初级卫生保健和健康教育活动。",
                            "TestPoint": "健康教育",
                            "Answer": "A",
                            "Difficulty": "易",
                            "SelectedItems": [
                                {
                                    "HasImg": 1,
                                    "ItemName": "A",
                                    "Content": "提高全人类整体的身体素质"
                                },
                                {
                                    "HasImg": 0,
                                    "ItemName": "B",
                                    "Content": "消除或降低危险因素，降低发病率、伤残率、死亡率"
                                },
                                {
                                    "HasImg": 0,
                                    "ItemName": "C",
                                    "Content": "提高生活和生命质量，并对教育效果作出评价"
                                },
                                {
                                    "HasImg": 0,
                                    "ItemName": "D",
                                    "Content": "改善、达到、维持和促进个体和社会健康的一种有效手段"
                                },
                                {
                                    "HasImg": 0,
                                    "ItemName": "E",
                                    "Content": "帮助人们建立和选择健康的生活方式"
                                }
                            ],
                            "StyleType": "ATEST",
                            "AllTestID": 43002887,
                            "ATestID": 43002887,
                            "SrcID": 9,
                            "SbjID": 45,
                            "CptID": 161,
                            "IsFav": 0,
                            "UserNoteContent": "",
                            "DealInfo": ""
                        },
                        {
                            "Title": "97141e350e73506da694c5ae638b6bd95690c653a0af67f457822d609db0a2fea85d48469a5efb5d4280d96069a7afd3db86c5de50398075b603fa700286c639",
                            "Explain": "从事健康教育人员的行为规范主要内容、健康教育者应拥护所有公民的价值、尊严、潜力和独特性、强调所有医疗保健服务的根本的道德原则，尊重自主权、促进社会公平、积极推进行善和避免伤害",
                            "TestPoint": "健康教育",
                            "Answer": "D",
                            "Difficulty": "易",
                            "SelectedItems": [
                                {
                                    "HasImg": 1,
                                    "ItemName": "A",
                                    "Content": "健康教育者应拥护所有公民的价值、尊严、潜力和独特性"
                                },
                                {
                                    "HasImg": 0,
                                    "ItemName": "B",
                                    "Content": "强调所有医疗保健服务的根本的道德原则，尊重自主权"
                                },
                                {
                                    "HasImg": 0,
                                    "ItemName": "C",
                                    "Content": "促进社会公平"
                                },
                                {
                                    "HasImg": 0,
                                    "ItemName": "D",
                                    "Content": "促进、维持和改善个体、家庭和社区的健康"
                                },
                                {
                                    "HasImg": 0,
                                    "ItemName": "E",
                                    "Content": "积极推进行善和避免伤害"
                                }
                            ],
                            "StyleType": "ATEST",
                            "AllTestID": 43002888,
                            "ATestID": 43002888,
                            "SrcID": 9,
                            "SbjID": 45,
                            "CptID": 161,
                            "IsFav": 0,
                            "UserNoteContent": "",
                            "DealInfo": ""
                        },
                        {
                            "Title": "3cc9f3962ec7801bc98510487c15a0563011e494398385a05b2d862b3227c4e4c6ccef6d92ea9bed",
                            "Explain": "人类生态环境的危机主要表现1.自然环境污染（1）大气污染。（2）水污染。（3）噪声污染。（4）放射性污染。（5）食品污染。6）医院污染2.自然资源和生态环境破坏（1）森林草原资源的破坏。（2）水土流失，土壤沙化。（3）水资源的破坏。（4）矿藏资源的不合理开发和海洋环境污染。",
                            "TestPoint": "预防医学概述",
                            "Answer": "B",
                            "Difficulty": "易",
                            "SelectedItems": [
                                {
                                    "HasImg": 1,
                                    "ItemName": "A",
                                    "Content": "社会环境的污染"
                                },
                                {
                                    "HasImg": 0,
                                    "ItemName": "B",
                                    "Content": "自然资源和生态环境的破坏"
                                },
                                {
                                    "HasImg": 0,
                                    "ItemName": "C",
                                    "Content": "人类生存环境的破坏，引发经济危机"
                                },
                                {
                                    "HasImg": 0,
                                    "ItemName": "D",
                                    "Content": "生态环境的危机，影响农业的发展"
                                },
                                {
                                    "HasImg": 0,
                                    "ItemName": "E",
                                    "Content": "自然资源的破坏性开采，引发经济危机"
                                }
                            ],
                            "StyleType": "ATEST",
                            "AllTestID": 43002889,
                            "ATestID": 43002889,
                            "SrcID": 9,
                            "SbjID": 45,
                            "CptID": 161,
                            "IsFav": 0,
                            "UserNoteContent": "",
                            "DealInfo": ""
                        },
                        {
                            "Title": "052c1e9c8bcb7fb42af60c8bc2e2fcdccb20ac76a755a9400bcd8f74210ef7e1561a98076ffcb62390c83e8109d5c129",
                            "Explain": "保护生态环境的道德基本内容包括：①热爱大自然，与自然为友；②爱惜动植物，保护生态平衡；③优化生产方法，防止环境污染；④发展科学技术，合理利用自然资源；⑤节俭资源消费，生活方式实现生态化。",
                            "TestPoint": "预防医学概述",
                            "Answer": "C",
                            "Difficulty": "易",
                            "SelectedItems": [
                                {
                                    "HasImg": 1,
                                    "ItemName": "A",
                                    "Content": "热爱大自然，与自然为友"
                                },
                                {
                                    "HasImg": 0,
                                    "ItemName": "B",
                                    "Content": "优化生产方式，防止环境污染"
                                },
                                {
                                    "HasImg": 0,
                                    "ItemName": "C",
                                    "Content": "对保护有关生态环境的各种设施人人有责"
                                },
                                {
                                    "HasImg": 0,
                                    "ItemName": "D",
                                    "Content": "发展科学技术，合理利用自然资源，节约资源消费，生活方式实现生态化"
                                },
                                {
                                    "HasImg": 0,
                                    "ItemName": "E",
                                    "Content": "爱惜动植物，保护生态平衡"
                                }
                            ],
                            "StyleType": "ATEST",
                            "AllTestID": 43002890,
                            "ATestID": 43002890,
                            "SrcID": 9,
                            "SbjID": 45,
                            "CptID": 161,
                            "IsFav": 0,
                            "UserNoteContent": "",
                            "DealInfo": ""
                        },
                        {
                            "Title": "d2f28a47c06e4777c5ecba0d8c2efcf904d82e8c47c7cce85085b13e52b7a82f0bd64d081c4315591212401d7bd3c084641918c2a75dbab58cc1a8a1eb7ce5f0",
                            "Explain": "1.尊重自然的道德原则。2.合理利用资源的道德原则。3.系统综合的道德原则。4.同步效应的道德原则。5.面向未来的道德原则。",
                            "TestPoint": "预防医学概述",
                            "Answer": "D",
                            "Difficulty": "易",
                            "SelectedItems": [
                                {
                                    "HasImg": 1,
                                    "ItemName": "A",
                                    "Content": "尊重自然的道德原则"
                                },
                                {
                                    "HasImg": 0,
                                    "ItemName": "B",
                                    "Content": "合理利用资源道德原则"
                                },
                                {
                                    "HasImg": 0,
                                    "ItemName": "C",
                                    "Content": "系统综合和同步效应的道德原则"
                                },
                                {
                                    "HasImg": 0,
                                    "ItemName": "D",
                                    "Content": "从自系统本单位制定运筹规划、落实措施的道德原则"
                                },
                                {
                                    "HasImg": 0,
                                    "ItemName": "E",
                                    "Content": "面向未来的道德原则"
                                }
                            ],
                            "StyleType": "ATEST",
                            "AllTestID": 43002891,
                            "ATestID": 43002891,
                            "SrcID": 9,
                            "SbjID": 45,
                            "CptID": 161,
                            "IsFav": 0,
                            "UserNoteContent": "",
                            "DealInfo": ""
                        },
                        {
                            "Title": "dd346b26ef529fac4e241107175ff8c871e25bc43114b6b1fd5420279ed5341a94d5c3210070225afe6e1bf3d3c74d1d42a5789bbc68cec4",
                            "Explain": "医务人员在环境保护中，道德责任的表现坚持眼前利益服从长远利益,物质与精神同步建设的道德责任",
                            "TestPoint": "环境保护",
                            "Answer": "C",
                            "Difficulty": "易",
                            "SelectedItems": [
                                {
                                    "HasImg": 1,
                                    "ItemName": "A",
                                    "Content": "自觉遵守刑事、民事法规"
                                },
                                {
                                    "HasImg": 0,
                                    "ItemName": "B",
                                    "Content": "加强对社会性污染的监测、管理的道德责任"
                                },
                                {
                                    "HasImg": 0,
                                    "ItemName": "C",
                                    "Content": "坚持眼前利益服从长远利益，物质与精神同步建设的道德责任"
                                },
                                {
                                    "HasImg": 0,
                                    "ItemName": "D",
                                    "Content": "适当允许先生产后污染治理、实现环境与经济同步发展的道德责任"
                                },
                                {
                                    "HasImg": 0,
                                    "ItemName": "E",
                                    "Content": "少数服从多数利益，认真履行环境道德的社会责任"
                                }
                            ],
                            "StyleType": "ATEST",
                            "AllTestID": 43002892,
                            "ATestID": 43002892,
                            "SrcID": 9,
                            "SbjID": 45,
                            "CptID": 161,
                            "IsFav": 0,
                            "UserNoteContent": "",
                            "DealInfo": ""
                        },
                        {
                            "Title": "63ac6331aa14c184800571023f74ef0aa20013144ee762f4447a229e97348be6b361de55b3c93d5307b9c937ef0077e4bb8b448a81bd881f",
                            "Explain": "卫生服务公平性是根据人各自的卫生需要不同，都有同等机会享受到相对应的基本的预防和（或）医疗和（或）保健和（或）康复的原则和属性。",
                            "TestPoint": "",
                            "Answer": "C",
                            "Difficulty": "",
                            "SelectedItems": [
                                {
                                    "ItemName": "A",
                                    "Content": "以社会阶层为导向"
                                },
                                {
                                    "ItemName": "B",
                                    "Content": "以支付能力为导向"
                                },
                                {
                                    "ItemName": "C",
                                    "Content": "以需要为导向"
                                },
                                {
                                    "ItemName": "D",
                                    "Content": "以市场经济规律为导向"
                                },
                                {
                                    "ItemName": "E",
                                    "Content": "患者年龄为导向"
                                }
                            ],
                            "StyleType": "ATEST",
                            "AllTestID": 43015796,
                            "ATestID": 43015796,
                            "SrcID": 9,
                            "SbjID": 45,
                            "CptID": 161,
                            "IsFav": 0,
                            "UserNoteContent": "",
                            "DealInfo": ""
                        },
                        {
                            "Title": "b931904abaea81851fc0fe4bc2a72a31ffe88922f68be19c5a3bfe0d5bbba709b499cd556c34b4ea",
                            "Explain": "从以上五个备选答案中不难分析出D选项是错误的，因为单独某个防疫工作者不可能有权利采取切断传染病传播途径的各种措施。必须根据疫情和传染病的传播途径才能采取具体措施。",
                            "TestPoint": "",
                            "Answer": "D",
                            "Difficulty": "",
                            "SelectedItems": [
                                {
                                    "ItemName": "A",
                                    "Content": "爱岗敬业，宣传大卫生法规，言传身教"
                                },
                                {
                                    "ItemName": "B",
                                    "Content": "改善工作和学习环境，严把防疫和食品卫生规定"
                                },
                                {
                                    "ItemName": "C",
                                    "Content": "严格监管，控制污染，保护生态环境，促进社会文明，科学严谨，实事求是，信息透明公开"
                                },
                                {
                                    "ItemName": "D",
                                    "Content": "防疫工作者有权在疫区采取切断传染病传播途径的各种措施"
                                },
                                {
                                    "ItemName": "E",
                                    "Content": "提高社区服务水平，保障妇女儿童和老年人权益"
                                }
                            ],
                            "StyleType": "ATEST",
                            "AllTestID": 43015797,
                            "ATestID": 43015797,
                            "SrcID": 9,
                            "SbjID": 45,
                            "CptID": 161,
                            "IsFav": 0,
                            "UserNoteContent": "",
                            "DealInfo": ""
                        }
                    ]
                },
                {
                    "StyleID": 5,
                    "Style": "A1/A2型题",
                    "Explain": "A1/A2型题：每一道考试题下面有A、B、C、D、E五个备选答案。请从中选择一个最佳答案。",
                    "Score": 1,
                    "Type": "ATEST",
                    "SubType": "",
                    "TestCount": 2,
                    "TestItems": [
                        {
                            "Title": "cab128f097de605ff05870ddd981a51a47a0bb83327325f2a848f9037a740d20c5a5a86e84cad30dc9f3ff22fcd18052d6eecd6f935e49be83700610e212ca99",
                            "Explain": "\"2000年人人享有卫生保健\"的基本政策：①健康是人的一项基本权利，是全世界的一项社会目标。故选B。②在各国内部和各国之间平均分配卫生资源，以便普遍都能得到初级卫生保健及其支持性服务。③人民有权利也有义务单独地和集体地参加卫生保健的计划和实施工作。④政府对其人民的健康负有责任，这种责任只能通过采取适当的卫生和其他社会措施来实现。⑤各国要使自己的全体人民都健康，必须在卫生事业中发挥各自的积极性。制定和实施卫生策略，需要有国际合作，但必须尊重本国的自力更生的精神。⑥需要社会和经济部门协调一致地工作，特别是要搞好同农业、畜牧业、粮食、工业、教育、住房公共工程、交通等部门的协作。⑦必须更加充分和更好地利用世界资源来促进卫生事业的发展。",
                            "TestPoint": "",
                            "Answer": "B",
                            "Difficulty": "",
                            "SelectedItems": [
                                {
                                    "HasImg": 1,
                                    "ItemName": "A",
                                    "Content": "人人不得病"
                                },
                                {
                                    "HasImg": 0,
                                    "ItemName": "B",
                                    "Content": "健康是人的一项基本权利"
                                },
                                {
                                    "HasImg": 0,
                                    "ItemName": "C",
                                    "Content": "全民免费医疗"
                                },
                                {
                                    "HasImg": 0,
                                    "ItemName": "D",
                                    "Content": "建立足够的大医院"
                                },
                                {
                                    "HasImg": 0,
                                    "ItemName": "E",
                                    "Content": "医疗保险"
                                }
                            ],
                            "StyleType": "ATEST",
                            "AllTestID": 41000697,
                            "ATestID": 41000697,
                            "SrcID": 9,
                            "SbjID": 45,
                            "CptID": 161,
                            "IsFav": 0,
                            "UserNoteContent": "",
                            "DealInfo": ""
                        },
                        {
                            "Title": "d03e179327c7bf846efa1749d86236b6bb1ff94bf351aa6b468c64614d63f8943e1004eb9e85d44ce27902e5ea46f2cda8049053bea86dd2c460c8592d44af39403eb73b90a824aec73c1b10cf333b8d",
                            "Explain": "社区健康教育是指根据医院负责的社区居民或医疗合同单位职工的需求，配合医疗保健服务而实施的健康教育计划。社区健康教育是在当地健康教育机构的指导和合作下，以医院医疗保健人员为主体，以社区群众为对象的教育活动。故选B。",
                            "TestPoint": "",
                            "Answer": "B",
                            "Difficulty": "",
                            "SelectedItems": [
                                {
                                    "HasImg": 1,
                                    "ItemName": "A",
                                    "Content": "以促进社区居民健康为宗旨"
                                },
                                {
                                    "HasImg": 0,
                                    "ItemName": "B",
                                    "Content": "以提高社区卫生机构经济效益为目标"
                                },
                                {
                                    "HasImg": 0,
                                    "ItemName": "C",
                                    "Content": "以社区居民为对象"
                                },
                                {
                                    "HasImg": 0,
                                    "ItemName": "D",
                                    "Content": "有组织、有计划、有评价的活动"
                                },
                                {
                                    "HasImg": 0,
                                    "ItemName": "E",
                                    "Content": "以社区为单位"
                                }
                            ],
                            "StyleType": "ATEST",
                            "AllTestID": 41000698,
                            "ATestID": 41000698,
                            "SrcID": 9,
                            "SbjID": 45,
                            "CptID": 161,
                            "IsFav": 0,
                            "UserNoteContent": "",
                            "DealInfo": ""
                        }
                    ]
                },
                {
                    "StyleID": 3,
                    "Style": "B1型题",
                    "Explain": "B1型题：以下提供若干组考题，每组考题共用在考题前列出的A、B、C、D、E五个备选答案。请从中选择一个与问题关系最密切的答案。某个备选答案可能被选择一次、多次或不被选择。",
                    "Score": 1,
                    "Type": "BTEST",
                    "SubType": "单项",
                    "TestCount": 2,
                    "TestItems": [
                        {
                            "Title": "a6640b840c2e3a07841b489fab511325",
                            "Explain": "1.病人和健康人都同时可以成为受试者，维护受试者的身心健康和安全，是人体实验的核心宗旨。",
                            "TestPoint": "",
                            "Answer": "E",
                            "Difficulty": "",
                            "StyleType": "BTEST",
                            "SubStyleType": "ATEST",
                            "FrontTitle": "",
                            "SelectedItems": [
                                {
                                    "ItemName": "A",
                                    "Content": "以病人作为受试对象的试验"
                                },
                                {
                                    "ItemName": "B",
                                    "Content": "保障受试者身心安全"
                                },
                                {
                                    "ItemName": "C",
                                    "Content": "人体实验时必须要做到真正的知情同意"
                                },
                                {
                                    "ItemName": "D",
                                    "Content": "选择受试者的时候需遵循的是"
                                },
                                {
                                    "ItemName": "E",
                                    "Content": "以人作为受试对象的试验是"
                                }
                            ],
                            "AllTestID": 43000625,
                            "BTestID": 43000183,
                            "SrcID": 9,
                            "SbjID": 45,
                            "CptID": 161,
                            "BTestItems": [
                                {
                                    "BTestItemID": 43000183,
                                    "Title": "a6640b840c2e3a07841b489fab511325",
                                    "Explain": "1.病人和健康人都同时可以成为受试者，维护受试者的身心健康和安全，是人体实验的核心宗旨。",
                                    "TestPoint": "",
                                    "Answer": "E",
                                    "DealInfo": ""
                                },
                                {
                                    "BTestItemID": 43000184,
                                    "Title": "385cda1bf76d71e718d9d5e2a0d6dc10",
                                    "Explain": "2.根据世界医学会的《赫尔辛基宣言》，.当科学的发展和受试者的健康发生矛盾时，后者的利益是至上的。选择受试者的时候需要遵循公平原则。",
                                    "TestPoint": "",
                                    "Answer": "D",
                                    "DealInfo": ""
                                }
                            ],
                            "IsFav": 0,
                            "UserNoteContent": ""
                        }
                    ]
                }
            ]
        },
        "isVip": 0,
        "testInfo": [
            {
                "AllTestID": 35000802,
                "ChildTableID": -1,
                "Correction": [],
                "Statistics": {
                    "Correction": [],
                    "Test": {
                        "AppID": 1328,
                        "AllTestID": 35000802,
                        "ChildTableID": -1,
                        "UserCount": 1006,
                        "RightCount": 850,
                        "FavCount": 6,
                        "DiscussionCount": 0,
                        "ExplainCount": 0,
                        "ConcernCount": 3
                    }
                },
                "Analysis": [],
                "KnowledgePoint": {
                    "Summary": null,
                    "KnowledgeText": null,
                    "AllTestID": 35000802,
                    "ChildTableID": -1
                },
                "DiscussionCount": 0,
                "ExplainCount": 0,
                "ConcernCount": 3
            },
            {
                "AllTestID": 43002874,
                "ChildTableID": -1,
                "Correction": [],
                "Statistics": {
                    "Correction": [],
                    "Test": {
                        "AppID": 1328,
                        "AllTestID": 43002874,
                        "ChildTableID": -1,
                        "UserCount": 1006,
                        "RightCount": 742,
                        "FavCount": 15,
                        "DiscussionCount": 0,
                        "ExplainCount": 0,
                        "ConcernCount": 7
                    }
                },
                "Analysis": [],
                "KnowledgePoint": {
                    "Summary": null,
                    "KnowledgeText": null,
                    "AllTestID": 43002874,
                    "ChildTableID": -1
                },
                "DiscussionCount": 0,
                "ExplainCount": 0,
                "ConcernCount": 7
            },
            {
                "AllTestID": 43002875,
                "ChildTableID": -1,
                "Correction": [],
                "Statistics": {
                    "Correction": [],
                    "Test": {
                        "AppID": 1328,
                        "AllTestID": 43002875,
                        "ChildTableID": -1,
                        "UserCount": 1061,
                        "RightCount": 721,
                        "FavCount": 16,
                        "DiscussionCount": 0,
                        "ExplainCount": 0,
                        "ConcernCount": 6
                    }
                },
                "Analysis": [],
                "KnowledgePoint": {
                    "Summary": null,
                    "KnowledgeText": null,
                    "AllTestID": 43002875,
                    "ChildTableID": -1
                },
                "DiscussionCount": 0,
                "ExplainCount": 0,
                "ConcernCount": 6
            },
            {
                "AllTestID": 43002876,
                "ChildTableID": -1,
                "Correction": [],
                "Statistics": {
                    "Correction": [],
                    "Test": {
                        "AppID": 1328,
                        "AllTestID": 43002876,
                        "ChildTableID": -1,
                        "UserCount": 1069,
                        "RightCount": 461,
                        "FavCount": 28,
                        "DiscussionCount": 0,
                        "ExplainCount": 0,
                        "ConcernCount": 10
                    }
                },
                "Analysis": [],
                "KnowledgePoint": {
                    "Summary": null,
                    "KnowledgeText": null,
                    "AllTestID": 43002876,
                    "ChildTableID": -1
                },
                "DiscussionCount": 0,
                "ExplainCount": 0,
                "ConcernCount": 10
            },
            {
                "AllTestID": 43002878,
                "ChildTableID": -1,
                "Correction": [],
                "Statistics": {
                    "Correction": [],
                    "Test": {
                        "AppID": 1328,
                        "AllTestID": 43002878,
                        "ChildTableID": -1,
                        "UserCount": 1022,
                        "RightCount": 521,
                        "FavCount": 24,
                        "DiscussionCount": 0,
                        "ExplainCount": 0,
                        "ConcernCount": 6
                    }
                },
                "Analysis": [],
                "KnowledgePoint": {
                    "Summary": null,
                    "KnowledgeText": null,
                    "AllTestID": 43002878,
                    "ChildTableID": -1
                },
                "DiscussionCount": 0,
                "ExplainCount": 0,
                "ConcernCount": 6
            },
            {
                "AllTestID": 43002879,
                "ChildTableID": -1,
                "Correction": [],
                "Statistics": {
                    "Correction": [],
                    "Test": {
                        "AppID": 1328,
                        "AllTestID": 43002879,
                        "ChildTableID": -1,
                        "UserCount": 922,
                        "RightCount": 718,
                        "FavCount": 15,
                        "DiscussionCount": 0,
                        "ExplainCount": 0,
                        "ConcernCount": 4
                    }
                },
                "Analysis": [],
                "KnowledgePoint": {
                    "Summary": null,
                    "KnowledgeText": null,
                    "AllTestID": 43002879,
                    "ChildTableID": -1
                },
                "DiscussionCount": 0,
                "ExplainCount": 0,
                "ConcernCount": 4
            },
            {
                "AllTestID": 43002880,
                "ChildTableID": -1,
                "Correction": [],
                "Statistics": {
                    "Correction": [],
                    "Test": {
                        "AppID": 1328,
                        "AllTestID": 43002880,
                        "ChildTableID": -1,
                        "UserCount": 914,
                        "RightCount": 690,
                        "FavCount": 10,
                        "DiscussionCount": 0,
                        "ExplainCount": 0,
                        "ConcernCount": 9
                    }
                },
                "Analysis": [],
                "KnowledgePoint": {
                    "Summary": null,
                    "KnowledgeText": null,
                    "AllTestID": 43002880,
                    "ChildTableID": -1
                },
                "DiscussionCount": 0,
                "ExplainCount": 0,
                "ConcernCount": 9
            },
            {
                "AllTestID": 43002881,
                "ChildTableID": -1,
                "Correction": [],
                "Statistics": {
                    "Correction": [],
                    "Test": {
                        "AppID": 1328,
                        "AllTestID": 43002881,
                        "ChildTableID": -1,
                        "UserCount": 985,
                        "RightCount": 483,
                        "FavCount": 32,
                        "DiscussionCount": 0,
                        "ExplainCount": 0,
                        "ConcernCount": 5
                    }
                },
                "Analysis": [],
                "KnowledgePoint": {
                    "Summary": null,
                    "KnowledgeText": null,
                    "AllTestID": 43002881,
                    "ChildTableID": -1
                },
                "DiscussionCount": 0,
                "ExplainCount": 0,
                "ConcernCount": 5
            },
            {
                "AllTestID": 43002882,
                "ChildTableID": -1,
                "Correction": [],
                "Statistics": {
                    "Correction": [],
                    "Test": {
                        "AppID": 1328,
                        "AllTestID": 43002882,
                        "ChildTableID": -1,
                        "UserCount": 917,
                        "RightCount": 709,
                        "FavCount": 7,
                        "DiscussionCount": 0,
                        "ExplainCount": 0,
                        "ConcernCount": 4
                    }
                },
                "Analysis": [],
                "KnowledgePoint": {
                    "Summary": null,
                    "KnowledgeText": null,
                    "AllTestID": 43002882,
                    "ChildTableID": -1
                },
                "DiscussionCount": 0,
                "ExplainCount": 0,
                "ConcernCount": 4
            },
            {
                "AllTestID": 43002883,
                "ChildTableID": -1,
                "Correction": [],
                "Statistics": {
                    "Correction": [],
                    "Test": {
                        "AppID": 1328,
                        "AllTestID": 43002883,
                        "ChildTableID": -1,
                        "UserCount": 990,
                        "RightCount": 535,
                        "FavCount": 26,
                        "DiscussionCount": 0,
                        "ExplainCount": 0,
                        "ConcernCount": 13
                    }
                },
                "Analysis": [],
                "KnowledgePoint": {
                    "Summary": null,
                    "KnowledgeText": null,
                    "AllTestID": 43002883,
                    "ChildTableID": -1
                },
                "DiscussionCount": 0,
                "ExplainCount": 0,
                "ConcernCount": 13
            },
            {
                "AllTestID": 43002884,
                "ChildTableID": -1,
                "Correction": [],
                "Statistics": {
                    "Correction": [],
                    "Test": {
                        "AppID": 1328,
                        "AllTestID": 43002884,
                        "ChildTableID": -1,
                        "UserCount": 969,
                        "RightCount": 480,
                        "FavCount": 27,
                        "DiscussionCount": 0,
                        "ExplainCount": 0,
                        "ConcernCount": 5
                    }
                },
                "Analysis": [],
                "KnowledgePoint": {
                    "Summary": null,
                    "KnowledgeText": null,
                    "AllTestID": 43002884,
                    "ChildTableID": -1
                },
                "DiscussionCount": 0,
                "ExplainCount": 0,
                "ConcernCount": 5
            },
            {
                "AllTestID": 43002885,
                "ChildTableID": -1,
                "Correction": [],
                "Statistics": {
                    "Correction": [],
                    "Test": {
                        "AppID": 1328,
                        "AllTestID": 43002885,
                        "ChildTableID": -1,
                        "UserCount": 910,
                        "RightCount": 608,
                        "FavCount": 14,
                        "DiscussionCount": 0,
                        "ExplainCount": 0,
                        "ConcernCount": 6
                    }
                },
                "Analysis": [],
                "KnowledgePoint": {
                    "Summary": null,
                    "KnowledgeText": null,
                    "AllTestID": 43002885,
                    "ChildTableID": -1
                },
                "DiscussionCount": 0,
                "ExplainCount": 0,
                "ConcernCount": 6
            },
            {
                "AllTestID": 43002886,
                "ChildTableID": -1,
                "Correction": [],
                "Statistics": {
                    "Correction": [],
                    "Test": {
                        "AppID": 1328,
                        "AllTestID": 43002886,
                        "ChildTableID": -1,
                        "UserCount": 1005,
                        "RightCount": 404,
                        "FavCount": 24,
                        "DiscussionCount": 0,
                        "ExplainCount": 0,
                        "ConcernCount": 6
                    }
                },
                "Analysis": [],
                "KnowledgePoint": {
                    "Summary": null,
                    "KnowledgeText": null,
                    "AllTestID": 43002886,
                    "ChildTableID": -1
                },
                "DiscussionCount": 0,
                "ExplainCount": 0,
                "ConcernCount": 6
            },
            {
                "AllTestID": 43002887,
                "ChildTableID": -1,
                "Correction": [],
                "Statistics": {
                    "Correction": [],
                    "Test": {
                        "AppID": 1328,
                        "AllTestID": 43002887,
                        "ChildTableID": -1,
                        "UserCount": 975,
                        "RightCount": 492,
                        "FavCount": 19,
                        "DiscussionCount": 0,
                        "ExplainCount": 0,
                        "ConcernCount": 8
                    }
                },
                "Analysis": [],
                "KnowledgePoint": {
                    "Summary": null,
                    "KnowledgeText": null,
                    "AllTestID": 43002887,
                    "ChildTableID": -1
                },
                "DiscussionCount": 0,
                "ExplainCount": 0,
                "ConcernCount": 8
            },
            {
                "AllTestID": 43002888,
                "ChildTableID": -1,
                "Correction": [],
                "Statistics": {
                    "Correction": [],
                    "Test": {
                        "AppID": 1328,
                        "AllTestID": 43002888,
                        "ChildTableID": -1,
                        "UserCount": 998,
                        "RightCount": 363,
                        "FavCount": 27,
                        "DiscussionCount": 0,
                        "ExplainCount": 0,
                        "ConcernCount": 9
                    }
                },
                "Analysis": [],
                "KnowledgePoint": {
                    "Summary": null,
                    "KnowledgeText": null,
                    "AllTestID": 43002888,
                    "ChildTableID": -1
                },
                "DiscussionCount": 0,
                "ExplainCount": 0,
                "ConcernCount": 9
            },
            {
                "AllTestID": 43002889,
                "ChildTableID": -1,
                "Correction": [],
                "Statistics": {
                    "Correction": [],
                    "Test": {
                        "AppID": 1328,
                        "AllTestID": 43002889,
                        "ChildTableID": -1,
                        "UserCount": 864,
                        "RightCount": 677,
                        "FavCount": 8,
                        "DiscussionCount": 0,
                        "ExplainCount": 0,
                        "ConcernCount": 7
                    }
                },
                "Analysis": [],
                "KnowledgePoint": {
                    "Summary": null,
                    "KnowledgeText": null,
                    "AllTestID": 43002889,
                    "ChildTableID": -1
                },
                "DiscussionCount": 0,
                "ExplainCount": 0,
                "ConcernCount": 7
            },
            {
                "AllTestID": 43002890,
                "ChildTableID": -1,
                "Correction": [],
                "Statistics": {
                    "Correction": [],
                    "Test": {
                        "AppID": 1328,
                        "AllTestID": 43002890,
                        "ChildTableID": -1,
                        "UserCount": 944,
                        "RightCount": 497,
                        "FavCount": 12,
                        "DiscussionCount": 0,
                        "ExplainCount": 0,
                        "ConcernCount": 6
                    }
                },
                "Analysis": [],
                "KnowledgePoint": {
                    "Summary": null,
                    "KnowledgeText": null,
                    "AllTestID": 43002890,
                    "ChildTableID": -1
                },
                "DiscussionCount": 0,
                "ExplainCount": 0,
                "ConcernCount": 6
            },
            {
                "AllTestID": 43002891,
                "ChildTableID": -1,
                "Correction": [],
                "Statistics": {
                    "Correction": [],
                    "Test": {
                        "AppID": 1328,
                        "AllTestID": 43002891,
                        "ChildTableID": -1,
                        "UserCount": 880,
                        "RightCount": 603,
                        "FavCount": 17,
                        "DiscussionCount": 0,
                        "ExplainCount": 0,
                        "ConcernCount": 7
                    }
                },
                "Analysis": [],
                "KnowledgePoint": {
                    "Summary": null,
                    "KnowledgeText": null,
                    "AllTestID": 43002891,
                    "ChildTableID": -1
                },
                "DiscussionCount": 0,
                "ExplainCount": 0,
                "ConcernCount": 7
            },
            {
                "AllTestID": 43002892,
                "ChildTableID": -1,
                "Correction": [],
                "Statistics": {
                    "Correction": [],
                    "Test": {
                        "AppID": 1328,
                        "AllTestID": 43002892,
                        "ChildTableID": -1,
                        "UserCount": 909,
                        "RightCount": 489,
                        "FavCount": 18,
                        "DiscussionCount": 0,
                        "ExplainCount": 0,
                        "ConcernCount": 5
                    }
                },
                "Analysis": [],
                "KnowledgePoint": {
                    "Summary": null,
                    "KnowledgeText": null,
                    "AllTestID": 43002892,
                    "ChildTableID": -1
                },
                "DiscussionCount": 0,
                "ExplainCount": 0,
                "ConcernCount": 5
            },
            {
                "AllTestID": 43015796,
                "ChildTableID": -1,
                "Correction": [],
                "Statistics": {
                    "Correction": [],
                    "Test": {
                        "AppID": 1328,
                        "AllTestID": 43015796,
                        "ChildTableID": -1,
                        "UserCount": 777,
                        "RightCount": 643,
                        "FavCount": 6,
                        "DiscussionCount": 0,
                        "ExplainCount": 0,
                        "ConcernCount": 5
                    }
                },
                "Analysis": [],
                "KnowledgePoint": {
                    "Summary": null,
                    "KnowledgeText": null,
                    "AllTestID": 43015796,
                    "ChildTableID": -1
                },
                "DiscussionCount": 0,
                "ExplainCount": 0,
                "ConcernCount": 5
            },
            {
                "AllTestID": 43015797,
                "ChildTableID": -1,
                "Correction": [],
                "Statistics": {
                    "Correction": [],
                    "Test": {
                        "AppID": 1328,
                        "AllTestID": 43015797,
                        "ChildTableID": -1,
                        "UserCount": 837,
                        "RightCount": 455,
                        "FavCount": 16,
                        "DiscussionCount": 0,
                        "ExplainCount": 0,
                        "ConcernCount": 6
                    }
                },
                "Analysis": [],
                "KnowledgePoint": {
                    "Summary": null,
                    "KnowledgeText": null,
                    "AllTestID": 43015797,
                    "ChildTableID": -1
                },
                "DiscussionCount": 0,
                "ExplainCount": 0,
                "ConcernCount": 6
            },
            {
                "AllTestID": 41000697,
                "ChildTableID": -1,
                "Correction": [],
                "Statistics": {
                    "Correction": [],
                    "Test": {
                        "AppID": 1328,
                        "AllTestID": 41000697,
                        "ChildTableID": -1,
                        "UserCount": 840,
                        "RightCount": 612,
                        "FavCount": 8,
                        "DiscussionCount": 0,
                        "ExplainCount": 0,
                        "ConcernCount": 4
                    }
                },
                "Analysis": [],
                "KnowledgePoint": {
                    "Summary": null,
                    "KnowledgeText": null,
                    "AllTestID": 41000697,
                    "ChildTableID": -1
                },
                "DiscussionCount": 0,
                "ExplainCount": 0,
                "ConcernCount": 4
            },
            {
                "AllTestID": 41000698,
                "ChildTableID": -1,
                "Correction": [],
                "Statistics": {
                    "Correction": [],
                    "Test": {
                        "AppID": 1328,
                        "AllTestID": 41000698,
                        "ChildTableID": -1,
                        "UserCount": 809,
                        "RightCount": 670,
                        "FavCount": 2,
                        "DiscussionCount": 0,
                        "ExplainCount": 0,
                        "ConcernCount": 7
                    }
                },
                "Analysis": [],
                "KnowledgePoint": {
                    "Summary": null,
                    "KnowledgeText": null,
                    "AllTestID": 41000698,
                    "ChildTableID": -1
                },
                "DiscussionCount": 0,
                "ExplainCount": 0,
                "ConcernCount": 7
            },
            {
                "AllTestID": 43000625,
                "ChildTableID": 43000183,
                "Correction": [],
                "Statistics": {
                    "Correction": [],
                    "Test": {
                        "AppID": 1328,
                        "AllTestID": 43000625,
                        "ChildTableID": 43000183,
                        "UserCount": 929,
                        "RightCount": 470,
                        "FavCount": 17,
                        "DiscussionCount": 0,
                        "ExplainCount": 0,
                        "ConcernCount": 9
                    }
                },
                "Analysis": [],
                "KnowledgePoint": {
                    "Summary": null,
                    "KnowledgeText": null,
                    "AllTestID": 43000625,
                    "ChildTableID": 43000183
                },
                "DiscussionCount": 0,
                "ExplainCount": 0,
                "ConcernCount": 9
            },
            {
                "AllTestID": 43000625,
                "ChildTableID": 43000184,
                "Correction": [],
                "Statistics": {
                    "Correction": [],
                    "Test": {
                        "AppID": 1328,
                        "AllTestID": 43000625,
                        "ChildTableID": 43000184,
                        "UserCount": 856,
                        "RightCount": 526,
                        "FavCount": 13,
                        "DiscussionCount": 0,
                        "ExplainCount": 0,
                        "ConcernCount": 6
                    }
                },
                "Analysis": [],
                "KnowledgePoint": {
                    "Summary": null,
                    "KnowledgeText": null,
                    "AllTestID": 43000625,
                    "ChildTableID": 43000184
                },
                "DiscussionCount": 0,
                "ExplainCount": 0,
                "ConcernCount": 6
            }
        ],
        "info": [],
        "encoded": 1,
        "examHistoryID": 0,
        "yimoinfo": [],
        "UserTime": 0
    },
    "status": 200
}